[{"_id":1,"traitName":"Gossip","traitDesc":"Gregarious and quick to make friends, gain Charisma % chance to learn a Rumor when Spicing","characterEffectId":0,"traitScore":1,"actionType":18,"resultType":0,"traitGroupId":1,"traitGroupId2":0,"muEvent1":0,"muEvent2":0,"muEx1":0,"muEx2":0,"muEx3":0,"muEx4":0,"muEx5":0,"muAdd1":0,"muAdd2":0,"muAdd3":0,"faction":0,"zone":0},{"_id":2,"traitName":"Durable","traitDesc":"+25% Chance to Survive Death Saves","characterEffectId":0,"traitScore":1,"actionType":49,"resultType":0,"traitGroupId":1,"traitGroupId2":0,"muEvent1":0,"muEvent2":0,"muEx1":0,"muEx2":0,"muEx3":0,"muEx4":0,"muEx5":0,"muAdd1":0,"muAdd2":0,"muAdd3":0,"faction":0,"zone":0},{"_id":3,"traitName":"Seedy","traitDesc":"At home in the Spice Hall, gain +20% Morale bonus when Spicing","characterEffectId":0,"traitScore":1,"actionType":18,"resultType":0,"traitGroupId":1,"traitGroupId2":0,"muEvent1":0,"muEvent2":0,"muEx1":0,"muEx2":0,"muEx3":0,"muEx4":0,"muEx5":0,"muAdd1":0,"muAdd2":0,"muAdd3":0,"faction":0,"zone":0},{"_id":4,"traitName":"Professional","traitDesc":"Pay Rate increases by $2 every level","characterEffectId":0,"traitScore":-1,"actionType":21,"resultType":2,"traitGroupId":1,"traitGroupId2":0,"muEvent1":0,"muEvent2":0,"muEx1":0,"muEx2":0,"muEx3":0,"muEx4":0,"muEx5":0,"muAdd1":0,"muAdd2":0,"muAdd3":0,"faction":0,"zone":0},{"_id":5,"traitName":"Classically Trained","traitDesc":"","characterEffectId":100,"traitScore":1,"actionType":0,"resultType":0,"traitGroupId":1,"traitGroupId2":0,"muEvent1":0,"muEvent2":0,"muEx1":0,"muEx2":0,"muEx3":0,"muEx4":0,"muEx5":0,"muAdd1":0,"muAdd2":0,"muAdd3":0,"faction":0,"zone":0},{"_id":6,"traitName":"Wily","traitDesc":"","characterEffectId":137,"traitScore":1,"actionType":0,"resultType":0,"traitGroupId":1,"traitGroupId2":0,"muEvent1":0,"muEvent2":0,"muEx1":0,"muEx2":0,"muEx3":0,"muEx4":0,"muEx5":0,"muAdd1":0,"muAdd2":0,"muAdd3":0,"faction":0,"zone":0},{"_id":7,"traitName":"Proud","traitDesc":"Pay Rate increases by $1 every level, double Morale penalty if not paid when other Crew are paid ","characterEffectId":0,"traitScore":-1,"actionType":21,"resultType":1,"traitGroupId":1,"traitGroupId2":0,"muEvent1":0,"muEvent2":0,"muEx1":0,"muEx2":0,"muEx3":0,"muEx4":0,"muEx5":0,"muAdd1":0,"muAdd2":0,"muAdd3":0,"faction":0,"zone":0},{"_id":8,"traitName":"Charmer","traitDesc":"","characterEffectId":101,"traitScore":1,"actionType":0,"resultType":0,"traitGroupId":2,"traitGroupId2":0,"muEvent1":0,"muEvent2":0,"muEx1":0,"muEx2":0,"muEx3":0,"muEx4":0,"muEx5":0,"muAdd1":0,"muAdd2":0,"muAdd3":0,"faction":0,"zone":0},{"_id":9,"traitName":"Inspiring","traitDesc":"20% chance to gain permanent +1 Command Skill Bonus when leveling (max 12)","characterEffectId":0,"traitScore":2,"actionType":7,"resultType":0,"traitGroupId":2,"traitGroupId2":0,"muEvent1":0,"muEvent2":0,"muEx1":0,"muEx2":0,"muEx3":0,"muEx4":0,"muEx5":0,"muAdd1":0,"muAdd2":0,"muAdd3":0,"faction":0,"zone":0},{"_id":10,"traitName":"Mediator","traitDesc":"20% chance to gain permanent +1 Negotiate Skill Bonus when leveling (max 12)","characterEffectId":0,"traitScore":2,"actionType":24,"resultType":0,"traitGroupId":2,"traitGroupId2":0,"muEvent1":0,"muEvent2":0,"muEx1":0,"muEx2":0,"muEx3":0,"muEx4":0,"muEx5":0,"muAdd1":0,"muAdd2":0,"muAdd3":0,"faction":0,"zone":0},{"_id":11,"traitName":"Pacifist","traitDesc":"","characterEffectId":102,"traitScore":-1,"actionType":0,"resultType":0,"traitGroupId":2,"traitGroupId2":0,"muEvent1":0,"muEvent2":0,"muEx1":0,"muEx2":0,"muEx3":0,"muEx4":0,"muEx5":0,"muAdd1":0,"muAdd2":0,"muAdd3":0,"faction":0,"zone":0},{"_id":12,"traitName":"Magnetic","traitDesc":"Captivating personality keeps people in your orbit, 10% + Charisma chance that crew will not abandon when at critically low Morale, only if Officer or Captain","characterEffectId":219,"traitScore":2,"actionType":41,"resultType":0,"traitGroupId":2,"traitGroupId2":0,"muEvent1":0,"muEvent2":0,"muEx1":0,"muEx2":0,"muEx3":0,"muEx4":0,"muEx5":0,"muAdd1":0,"muAdd2":0,"muAdd3":0,"faction":0,"zone":0},{"_id":13,"traitName":"Obedient","traitDesc":"Pay Rate increase when leveling is 80% less likely","characterEffectId":0,"traitScore":1,"actionType":21,"resultType":2,"traitGroupId":2,"traitGroupId2":0,"muEvent1":0,"muEvent2":0,"muEx1":0,"muEx2":0,"muEx3":0,"muEx4":0,"muEx5":0,"muAdd1":0,"muAdd2":0,"muAdd3":0,"faction":0,"zone":0},{"_id":14,"traitName":"Storyteller","traitDesc":"Known for spinning engaging tales and cracking hilarious jokes, gains 30% + Charisma chance to increase Morale gains in Spice Hall by +2","characterEffectId":0,"traitScore":1,"actionType":18,"resultType":0,"traitGroupId":2,"traitGroupId2":0,"muEvent1":0,"muEvent2":0,"muEx1":0,"muEx2":0,"muEx3":0,"muEx4":0,"muEx5":0,"muAdd1":0,"muAdd2":0,"muAdd3":0,"faction":0,"zone":0},{"_id":15,"traitName":"Scrappy","traitDesc":"Tough to put down, +5% Death Save to survive lethal hit in any situation","characterEffectId":103,"traitScore":1,"actionType":49,"resultType":0,"traitGroupId":3,"traitGroupId2":0,"muEvent1":0,"muEvent2":0,"muEx1":0,"muEx2":0,"muEx3":0,"muEx4":0,"muEx5":0,"muAdd1":0,"muAdd2":0,"muAdd3":0,"faction":0,"zone":0},{"_id":16,"traitName":"Thick Skinned","traitDesc":"","characterEffectId":104,"traitScore":1,"actionType":0,"resultType":0,"traitGroupId":3,"traitGroupId2":0,"muEvent1":0,"muEvent2":0,"muEx1":0,"muEx2":0,"muEx3":0,"muEx4":0,"muEx5":0,"muAdd1":0,"muAdd2":0,"muAdd3":0,"faction":0,"zone":0},{"_id":17,"traitName":"Tank","traitDesc":"","characterEffectId":105,"traitScore":0,"actionType":0,"resultType":0,"traitGroupId":3,"traitGroupId2":0,"muEvent1":0,"muEvent2":0,"muEx1":0,"muEx2":0,"muEx3":0,"muEx4":0,"muEx5":0,"muAdd1":0,"muAdd2":0,"muAdd3":0,"faction":0,"zone":0},{"_id":18,"traitName":"Hardened Presence","traitDesc":"Dominant presence reduces cost of paying off mutineers by 10%","characterEffectId":218,"traitScore":2,"actionType":42,"resultType":0,"traitGroupId":3,"traitGroupId2":0,"muEvent1":0,"muEvent2":0,"muEx1":0,"muEx2":0,"muEx3":0,"muEx4":0,"muEx5":0,"muAdd1":0,"muAdd2":0,"muAdd3":0,"faction":0,"zone":0},{"_id":19,"traitName":"Bearbuilt","traitDesc":"","characterEffectId":134,"traitScore":1,"actionType":0,"resultType":0,"traitGroupId":3,"traitGroupId2":0,"muEvent1":0,"muEvent2":0,"muEx1":0,"muEx2":0,"muEx3":0,"muEx4":0,"muEx5":0,"muAdd1":0,"muAdd2":0,"muAdd3":0,"faction":0,"zone":0},{"_id":20,"traitName":"Rugged","traitDesc":"","characterEffectId":133,"traitScore":1,"actionType":0,"resultType":0,"traitGroupId":3,"traitGroupId2":0,"muEvent1":0,"muEvent2":0,"muEx1":0,"muEx2":0,"muEx3":0,"muEx4":0,"muEx5":0,"muAdd1":0,"muAdd2":0,"muAdd3":0,"faction":0,"zone":0},{"_id":21,"traitName":"Hard Hitting","traitDesc":"","characterEffectId":135,"traitScore":1,"actionType":0,"resultType":0,"traitGroupId":3,"traitGroupId2":0,"muEvent1":0,"muEvent2":0,"muEx1":0,"muEx2":0,"muEx3":0,"muEx4":0,"muEx5":0,"muAdd1":0,"muAdd2":0,"muAdd3":0,"faction":0,"zone":0},{"_id":22,"traitName":"Stubborn","traitDesc":"Once below 50 Morale, obstinately digs in on a grudge and all Morale gains are reduced by 50%","characterEffectId":148,"traitScore":-1,"actionType":61,"resultType":101,"traitGroupId":3,"traitGroupId2":0,"muEvent1":0,"muEvent2":0,"muEx1":0,"muEx2":0,"muEx3":0,"muEx4":0,"muEx5":0,"muAdd1":0,"muAdd2":0,"muAdd3":0,"faction":0,"zone":0},{"_id":23,"traitName":"Wanderlust","traitDesc":"Insatiable drive to travel can only be sated by new experiences, gain 5 to 10 Morale when orbiting a new world","characterEffectId":0,"traitScore":0,"actionType":17,"resultType":0,"traitGroupId":4,"traitGroupId2":0,"muEvent1":0,"muEvent2":0,"muEx1":0,"muEx2":0,"muEx3":0,"muEx4":0,"muEx5":0,"muAdd1":0,"muAdd2":0,"muAdd3":0,"faction":0,"zone":0},{"_id":24,"traitName":"Traveler","traitDesc":"Excited by far-flung travel, gains 3-6 Morale when making a Hyperwarp jump","characterEffectId":1139,"traitScore":1,"actionType":35,"resultType":0,"traitGroupId":4,"traitGroupId2":0,"muEvent1":0,"muEvent2":0,"muEx1":0,"muEx2":0,"muEx3":0,"muEx4":0,"muEx5":0,"muAdd1":0,"muAdd2":0,"muAdd3":0,"faction":0,"zone":0},{"_id":25,"traitName":"Listener","traitDesc":"Empathetic and approachable, a gain in Morale causes an equal gain for another crew member","characterEffectId":149,"traitScore":2,"actionType":61,"resultType":101,"traitGroupId":4,"traitGroupId2":0,"muEvent1":0,"muEvent2":0,"muEx1":0,"muEx2":0,"muEx3":0,"muEx4":0,"muEx5":0,"muAdd1":0,"muAdd2":0,"muAdd3":0,"faction":0,"zone":0},{"_id":26,"traitName":"Adventurous","traitDesc":"Exhilarated by wandering new and dangerous lands, gains a Resilience % chance to recover 3 to 5 Morale whenever Exploring","characterEffectId":0,"traitScore":1,"actionType":52,"resultType":0,"traitGroupId":4,"traitGroupId2":0,"muEvent1":0,"muEvent2":0,"muEx1":0,"muEx2":0,"muEx3":0,"muEx4":0,"muEx5":0,"muAdd1":0,"muAdd2":0,"muAdd3":0,"faction":0,"zone":0},{"_id":27,"traitName":"Other Fascination","traitDesc":"What might terrify others invokes an intense fascination, gain +6 Morale when encountering xeno ship","characterEffectId":0,"traitScore":0,"actionType":19,"resultType":0,"traitGroupId":4,"traitGroupId2":0,"muEvent1":0,"muEvent2":0,"muEx1":0,"muEx2":0,"muEx3":0,"muEx4":0,"muEx5":0,"muAdd1":0,"muAdd2":0,"muAdd3":0,"faction":0,"zone":0},{"_id":28,"traitName":"Gravity Sickness","traitDesc":"Illness from the savage pull of gravity, loss of 3 to 6 HP when landing on a world","characterEffectId":1140,"traitScore":-1,"actionType":15,"resultType":0,"traitGroupId":4,"traitGroupId2":0,"muEvent1":0,"muEvent2":0,"muEx1":0,"muEx2":0,"muEx3":0,"muEx4":0,"muEx5":0,"muAdd1":0,"muAdd2":0,"muAdd3":0,"faction":0,"zone":0},{"_id":29,"traitName":"Stormshock","traitDesc":"Afflicted by even the slightest radiation, loss of 3 to 10 HP and Morale when sailing through Radiation Storms","characterEffectId":0,"traitScore":-1,"actionType":20,"resultType":0,"traitGroupId":4,"traitGroupId2":0,"muEvent1":0,"muEvent2":0,"muEx1":0,"muEx2":0,"muEx3":0,"muEx4":0,"muEx5":0,"muAdd1":0,"muAdd2":0,"muAdd3":0,"faction":0,"zone":0},{"_id":30,"traitName":"Worldsick","traitDesc":"Security of gravity and spice hall are a reminder of the loneliness of space, loss of 1 to 4 Morale on landing on a world","characterEffectId":0,"traitScore":-1,"actionType":15,"resultType":0,"traitGroupId":5,"traitGroupId2":0,"muEvent1":0,"muEvent2":0,"muEx1":0,"muEx2":0,"muEx3":0,"muEx4":0,"muEx5":0,"muAdd1":0,"muAdd2":0,"muAdd3":0,"faction":0,"zone":0},{"_id":31,"traitName":"Moody","traitDesc":"Volatile temperament brings down energy, 50% to double all negative Morale changes","characterEffectId":150,"traitScore":0,"actionType":61,"resultType":101,"traitGroupId":5,"traitGroupId2":0,"muEvent1":0,"muEvent2":0,"muEx1":0,"muEx2":0,"muEx3":0,"muEx4":0,"muEx5":0,"muAdd1":0,"muAdd2":0,"muAdd3":0,"faction":0,"zone":0},{"_id":32,"traitName":"Earthy","traitDesc":"","characterEffectId":106,"traitScore":1,"actionType":0,"resultType":0,"traitGroupId":5,"traitGroupId2":0,"muEvent1":0,"muEvent2":0,"muEx1":0,"muEx2":0,"muEx3":0,"muEx4":0,"muEx5":0,"muAdd1":0,"muAdd2":0,"muAdd3":0,"faction":0,"zone":0},{"_id":33,"traitName":"Hyperwarp Sickness","traitDesc":"Wrenching experience of Hyperwarp travel causes sickness, loss of 3 to 10 HP when jumping Hyperwarp","characterEffectId":0,"traitScore":-1,"actionType":35,"resultType":0,"traitGroupId":5,"traitGroupId2":0,"muEvent1":0,"muEvent2":0,"muEx1":0,"muEx2":0,"muEx3":0,"muEx4":0,"muEx5":0,"muAdd1":0,"muAdd2":0,"muAdd3":0,"faction":0,"zone":0},{"_id":34,"traitName":"Earthbound Friends","traitDesc":"Charisma % chance to learn about a new Contact when Spicing in the Hall","characterEffectId":0,"traitScore":1,"actionType":18,"resultType":0,"traitGroupId":5,"traitGroupId2":0,"muEvent1":0,"muEvent2":0,"muEx1":0,"muEx2":0,"muEx3":0,"muEx4":0,"muEx5":0,"muAdd1":0,"muAdd2":0,"muAdd3":0,"faction":0,"zone":0},{"_id":35,"traitName":"Stout","traitDesc":"","characterEffectId":136,"traitScore":1,"actionType":0,"resultType":0,"traitGroupId":5,"traitGroupId2":0,"muEvent1":0,"muEvent2":0,"muEx1":0,"muEx2":0,"muEx3":0,"muEx4":0,"muEx5":0,"muAdd1":0,"muAdd2":0,"muAdd3":0,"faction":0,"zone":0},{"_id":36,"traitName":"Xenophobic","traitDesc":"Sickening dread paralyzes when encountering something alien, loss of 6 Morale when encountering xeno ship","characterEffectId":0,"traitScore":-1,"actionType":19,"resultType":0,"traitGroupId":5,"traitGroupId2":0,"muEvent1":0,"muEvent2":0,"muEx1":0,"muEx2":0,"muEx3":0,"muEx4":0,"muEx5":0,"muAdd1":0,"muAdd2":0,"muAdd3":0,"faction":0,"zone":0},{"_id":37,"traitName":"Focused","traitDesc":"","characterEffectId":141,"traitScore":1,"actionType":0,"resultType":0,"traitGroupId":6,"traitGroupId2":0,"muEvent1":0,"muEvent2":0,"muEx1":0,"muEx2":0,"muEx3":0,"muEx4":0,"muEx5":0,"muAdd1":0,"muAdd2":0,"muAdd3":0,"faction":0,"zone":0},{"_id":38,"traitName":"Steady","traitDesc":"Dependable and enduring, all Morale loss is reduced by 50%","characterEffectId":151,"traitScore":1,"actionType":61,"resultType":101,"traitGroupId":6,"traitGroupId2":0,"muEvent1":0,"muEvent2":0,"muEx1":0,"muEx2":0,"muEx3":0,"muEx4":0,"muEx5":0,"muAdd1":0,"muAdd2":0,"muAdd3":0,"faction":0,"zone":0},{"_id":39,"traitName":"Enduring","traitDesc":"","characterEffectId":107,"traitScore":2,"actionType":0,"resultType":0,"traitGroupId":6,"traitGroupId2":0,"muEvent1":0,"muEvent2":0,"muEx1":0,"muEx2":0,"muEx3":0,"muEx4":0,"muEx5":0,"muAdd1":0,"muAdd2":0,"muAdd3":0,"faction":0,"zone":0},{"_id":40,"traitName":"Fearless","traitDesc":"Never suffers a Morale Break in Crew Combat, regardless of how low Morale is","characterEffectId":0,"traitScore":2,"actionType":50,"resultType":0,"traitGroupId":6,"traitGroupId2":0,"muEvent1":0,"muEvent2":0,"muEx1":0,"muEx2":0,"muEx3":0,"muEx4":0,"muEx5":0,"muAdd1":0,"muAdd2":0,"muAdd3":0,"faction":0,"zone":0},{"_id":41,"traitName":"Valiant","traitDesc":"","characterEffectId":139,"traitScore":1,"actionType":0,"resultType":0,"traitGroupId":6,"traitGroupId2":0,"muEvent1":0,"muEvent2":0,"muEx1":0,"muEx2":0,"muEx3":0,"muEx4":0,"muEx5":0,"muAdd1":0,"muAdd2":0,"muAdd3":0,"faction":0,"zone":0},{"_id":42,"traitName":"Obdurate","traitDesc":"Stubborn and stuck in old ways, 25% chance of not gaining XP","characterEffectId":158,"traitScore":-1,"actionType":62,"resultType":102,"traitGroupId":6,"traitGroupId2":0,"muEvent1":0,"muEvent2":0,"muEx1":0,"muEx2":0,"muEx3":0,"muEx4":0,"muEx5":0,"muAdd1":0,"muAdd2":0,"muAdd3":0,"faction":0,"zone":0},{"_id":43,"traitName":"Calm","traitDesc":"","characterEffectId":147,"traitScore":2,"actionType":0,"resultType":0,"traitGroupId":7,"traitGroupId2":0,"muEvent1":0,"muEvent2":0,"muEx1":0,"muEx2":0,"muEx3":0,"muEx4":0,"muEx5":0,"muAdd1":0,"muAdd2":0,"muAdd3":0,"faction":0,"zone":0},{"_id":44,"traitName":"Iron Spine","traitDesc":"","characterEffectId":108,"traitScore":1,"actionType":0,"resultType":0,"traitGroupId":7,"traitGroupId2":0,"muEvent1":0,"muEvent2":0,"muEx1":0,"muEx2":0,"muEx3":0,"muEx4":0,"muEx5":0,"muAdd1":0,"muAdd2":0,"muAdd3":0,"faction":0,"zone":0},{"_id":45,"traitName":"Peacemaker","traitDesc":"Gain Morale whenever ending ship combat in Draw or Ransom, lose Morale when destroying enemy ship","characterEffectId":0,"traitScore":0,"actionType":86,"resultType":0,"traitGroupId":7,"traitGroupId2":0,"muEvent1":0,"muEvent2":0,"muEx1":0,"muEx2":0,"muEx3":0,"muEx4":0,"muEx5":0,"muAdd1":0,"muAdd2":0,"muAdd3":0,"faction":0,"zone":0},{"_id":46,"traitName":"Observant","traitDesc":"Always alert and wary of danger, reduces crew and ship damage by 10% whenever Exploring","characterEffectId":0,"traitScore":1,"actionType":52,"resultType":0,"traitGroupId":7,"traitGroupId2":0,"muEvent1":0,"muEvent2":0,"muEx1":0,"muEx2":0,"muEx3":0,"muEx4":0,"muEx5":0,"muAdd1":0,"muAdd2":0,"muAdd3":0,"faction":0,"zone":0},{"_id":47,"traitName":"Sharp Witted","traitDesc":"Astute and clever, +25% chance of gaining double XP","characterEffectId":159,"traitScore":2,"actionType":62,"resultType":102,"traitGroupId":8,"traitGroupId2":0,"muEvent1":0,"muEvent2":0,"muEx1":0,"muEx2":0,"muEx3":0,"muEx4":0,"muEx5":0,"muAdd1":0,"muAdd2":0,"muAdd3":0,"faction":0,"zone":0},{"_id":48,"traitName":"Scrounger","traitDesc":"Naturally voracious seeker, gain +10% rewards whenever Exploring","characterEffectId":1141,"traitScore":1,"actionType":52,"resultType":0,"traitGroupId":8,"traitGroupId2":0,"muEvent1":0,"muEvent2":0,"muEx1":0,"muEx2":0,"muEx3":0,"muEx4":0,"muEx5":0,"muAdd1":0,"muAdd2":0,"muAdd3":0,"faction":0,"zone":0},{"_id":49,"traitName":"Risky","traitDesc":"","characterEffectId":109,"traitScore":0,"actionType":0,"resultType":0,"traitGroupId":8,"traitGroupId2":0,"muEvent1":0,"muEvent2":0,"muEx1":0,"muEx2":0,"muEx3":0,"muEx4":0,"muEx5":0,"muAdd1":0,"muAdd2":0,"muAdd3":0,"faction":0,"zone":0},{"_id":50,"traitName":"Mysterious","traitDesc":"Perplexing and good at hiding the truth of things, this one has 50% resistance to hidden Traits being discovered","characterEffectId":0,"traitScore":-1,"actionType":0,"resultType":0,"traitGroupId":8,"traitGroupId2":0,"muEvent1":0,"muEvent2":0,"muEx1":0,"muEx2":0,"muEx3":0,"muEx4":0,"muEx5":0,"muAdd1":0,"muAdd2":0,"muAdd3":0,"faction":0,"zone":0},{"_id":51,"traitName":"Klepto","traitDesc":"","characterEffectId":140,"traitScore":-1,"actionType":0,"resultType":0,"traitGroupId":8,"traitGroupId2":0,"muEvent1":0,"muEvent2":0,"muEx1":0,"muEx2":0,"muEx3":0,"muEx4":0,"muEx5":0,"muAdd1":0,"muAdd2":0,"muAdd3":0,"faction":0,"zone":0},{"_id":52,"traitName":"Shrewd","traitDesc":"","characterEffectId":110,"traitScore":1,"actionType":0,"resultType":0,"traitGroupId":8,"traitGroupId2":0,"muEvent1":0,"muEvent2":0,"muEx1":0,"muEx2":0,"muEx3":0,"muEx4":0,"muEx5":0,"muAdd1":0,"muAdd2":0,"muAdd3":0,"faction":0,"zone":0},{"_id":53,"traitName":"Tense","traitDesc":"","characterEffectId":111,"traitScore":1,"actionType":0,"resultType":0,"traitGroupId":8,"traitGroupId2":0,"muEvent1":0,"muEvent2":0,"muEx1":0,"muEx2":0,"muEx3":0,"muEx4":0,"muEx5":0,"muAdd1":0,"muAdd2":0,"muAdd3":0,"faction":0,"zone":0},{"_id":54,"traitName":"Sly","traitDesc":"Artful in devious craft, gain +10% Intel Record rewards whenever Spying (max 30%)","characterEffectId":0,"traitScore":1,"actionType":54,"resultType":0,"traitGroupId":8,"traitGroupId2":0,"muEvent1":0,"muEvent2":0,"muEx1":0,"muEx2":0,"muEx3":0,"muEx4":0,"muEx5":0,"muAdd1":0,"muAdd2":0,"muAdd3":0,"faction":0,"zone":0},{"_id":55,"traitName":"Dead Aim","traitDesc":"","characterEffectId":112,"traitScore":1,"actionType":0,"resultType":0,"traitGroupId":9,"traitGroupId2":0,"muEvent1":0,"muEvent2":0,"muEx1":0,"muEx2":0,"muEx3":0,"muEx4":0,"muEx5":0,"muAdd1":0,"muAdd2":0,"muAdd3":0,"faction":0,"zone":0},{"_id":56,"traitName":"Blind Focus","traitDesc":"","characterEffectId":113,"traitScore":0,"actionType":0,"resultType":0,"traitGroupId":9,"traitGroupId2":0,"muEvent1":0,"muEvent2":0,"muEx1":0,"muEx2":0,"muEx3":0,"muEx4":0,"muEx5":0,"muAdd1":0,"muAdd2":0,"muAdd3":0,"faction":0,"zone":0},{"_id":57,"traitName":"Concentration","traitDesc":"","characterEffectId":114,"traitScore":1,"actionType":0,"resultType":0,"traitGroupId":9,"traitGroupId2":0,"muEvent1":0,"muEvent2":0,"muEx1":0,"muEx2":0,"muEx3":0,"muEx4":0,"muEx5":0,"muAdd1":0,"muAdd2":0,"muAdd3":0,"faction":0,"zone":0},{"_id":58,"traitName":"Virtuous","traitDesc":"Proud to do the right thing, gains a Wisdom % chance to recover 3 to 5 Morale whenever Patrolling","characterEffectId":0,"traitScore":1,"actionType":56,"resultType":0,"traitGroupId":9,"traitGroupId2":0,"muEvent1":0,"muEvent2":0,"muEx1":0,"muEx2":0,"muEx3":0,"muEx4":0,"muEx5":0,"muAdd1":0,"muAdd2":0,"muAdd3":0,"faction":0,"zone":0},{"_id":59,"traitName":"Ill-Tempered","traitDesc":"Surly and morose, Morale never rises above 80","characterEffectId":152,"traitScore":-1,"actionType":61,"resultType":0,"traitGroupId":9,"traitGroupId2":0,"muEvent1":0,"muEvent2":0,"muEx1":0,"muEx2":0,"muEx3":0,"muEx4":0,"muEx5":0,"muAdd1":0,"muAdd2":0,"muAdd3":0,"faction":0,"zone":0},{"_id":60,"traitName":"Fleet footed","traitDesc":"","characterEffectId":115,"traitScore":1,"actionType":0,"resultType":0,"traitGroupId":10,"traitGroupId2":0,"muEvent1":0,"muEvent2":0,"muEx1":0,"muEx2":0,"muEx3":0,"muEx4":0,"muEx5":0,"muAdd1":0,"muAdd2":0,"muAdd3":0,"faction":0,"zone":0},{"_id":61,"traitName":"Acrobatic","traitDesc":"","characterEffectId":99,"traitScore":2,"actionType":0,"resultType":0,"traitGroupId":10,"traitGroupId2":0,"muEvent1":0,"muEvent2":0,"muEx1":0,"muEx2":0,"muEx3":0,"muEx4":0,"muEx5":0,"muAdd1":0,"muAdd2":0,"muAdd3":0,"faction":0,"zone":0},{"_id":62,"traitName":"Discreet","traitDesc":"20% chance to gain permanent +1 Stealth Skill Bonus when leveling (max 12)","characterEffectId":0,"traitScore":2,"actionType":25,"resultType":0,"traitGroupId":10,"traitGroupId2":0,"muEvent1":0,"muEvent2":0,"muEx1":0,"muEx2":0,"muEx3":0,"muEx4":0,"muEx5":0,"muAdd1":0,"muAdd2":0,"muAdd3":0,"faction":0,"zone":0},{"_id":63,"traitName":"Precise","traitDesc":"","characterEffectId":116,"traitScore":1,"actionType":0,"resultType":0,"traitGroupId":10,"traitGroupId2":0,"muEvent1":0,"muEvent2":0,"muEx1":0,"muEx2":0,"muEx3":0,"muEx4":0,"muEx5":0,"muAdd1":0,"muAdd2":0,"muAdd3":0,"faction":0,"zone":0},{"_id":64,"traitName":"Twitchy","traitDesc":"","characterEffectId":117,"traitScore":0,"actionType":0,"resultType":0,"traitGroupId":10,"traitGroupId2":0,"muEvent1":0,"muEvent2":0,"muEx1":0,"muEx2":0,"muEx3":0,"muEx4":0,"muEx5":0,"muAdd1":0,"muAdd2":0,"muAdd3":0,"faction":0,"zone":0},{"_id":65,"traitName":"Mechsync","traitDesc":"20% chance to gain permanent +1 Repair Skill Bonus when leveling (max 12)","characterEffectId":1142,"traitScore":2,"actionType":6,"resultType":0,"traitGroupId":11,"traitGroupId2":0,"muEvent1":0,"muEvent2":0,"muEx1":0,"muEx2":0,"muEx3":0,"muEx4":0,"muEx5":0,"muAdd1":0,"muAdd2":0,"muAdd3":0,"faction":0,"zone":0},{"_id":66,"traitName":"Vandal","traitDesc":"When boarding, +10% Dmg to enemy ship components","characterEffectId":0,"traitScore":1,"actionType":77,"resultType":0,"traitGroupId":11,"traitGroupId2":0,"muEvent1":0,"muEvent2":0,"muEx1":0,"muEx2":0,"muEx3":0,"muEx4":0,"muEx5":0,"muAdd1":0,"muAdd2":0,"muAdd3":0,"faction":0,"zone":0},{"_id":67,"traitName":"Spatial","traitDesc":"20% chance to gain permanent +1 Pilot Skill Bonus when leveling (max 12)","characterEffectId":1143,"traitScore":2,"actionType":2,"resultType":0,"traitGroupId":11,"traitGroupId2":0,"muEvent1":0,"muEvent2":0,"muEx1":0,"muEx2":0,"muEx3":0,"muEx4":0,"muEx5":0,"muAdd1":0,"muAdd2":0,"muAdd3":0,"faction":0,"zone":0},{"_id":68,"traitName":"Acid Burnt","traitDesc":"","characterEffectId":118,"traitScore":1,"actionType":0,"resultType":0,"traitGroupId":11,"traitGroupId2":0,"muEvent1":0,"muEvent2":0,"muEx1":0,"muEx2":0,"muEx3":0,"muEx4":0,"muEx5":0,"muAdd1":0,"muAdd2":0,"muAdd3":0,"faction":0,"zone":0},{"_id":69,"traitName":"Sharpshooter","traitDesc":"","characterEffectId":119,"traitScore":1,"actionType":0,"resultType":0,"traitGroupId":11,"traitGroupId2":0,"muEvent1":0,"muEvent2":0,"muEx1":0,"muEx2":0,"muEx3":0,"muEx4":0,"muEx5":0,"muAdd1":0,"muAdd2":0,"muAdd3":0,"faction":0,"zone":0},{"_id":70,"traitName":"Vulture","traitDesc":"Adept at picking over the wreck for valuable scrap, gain +10% credits when Salvaging enemy ship or orbital (max 30%)","characterEffectId":0,"traitScore":0,"actionType":75,"resultType":0,"traitGroupId":11,"traitGroupId2":0,"muEvent1":0,"muEvent2":0,"muEx1":0,"muEx2":0,"muEx3":0,"muEx4":0,"muEx5":0,"muAdd1":0,"muAdd2":0,"muAdd3":0,"faction":0,"zone":0},{"_id":71,"traitName":"Device Freak","traitDesc":"Special obsession with tech and devices allows equip of 2nd Gear slot, only if Officer or Captain","characterEffectId":1144,"traitScore":2,"actionType":0,"resultType":0,"traitGroupId":11,"traitGroupId2":0,"muEvent1":0,"muEvent2":0,"muEx1":0,"muEx2":0,"muEx3":0,"muEx4":0,"muEx5":0,"muAdd1":0,"muAdd2":0,"muAdd3":0,"faction":0,"zone":0},{"_id":72,"traitName":"Ex-Military","traitDesc":"","characterEffectId":120,"traitScore":1,"actionType":0,"resultType":0,"traitGroupId":12,"traitGroupId2":0,"muEvent1":0,"muEvent2":0,"muEx1":0,"muEx2":0,"muEx3":0,"muEx4":0,"muEx5":0,"muAdd1":0,"muAdd2":0,"muAdd3":0,"faction":0,"zone":0},{"_id":73,"traitName":"Brave","traitDesc":"","characterEffectId":121,"traitScore":1,"actionType":0,"resultType":0,"traitGroupId":12,"traitGroupId2":0,"muEvent1":0,"muEvent2":0,"muEx1":0,"muEx2":0,"muEx3":0,"muEx4":0,"muEx5":0,"muAdd1":0,"muAdd2":0,"muAdd3":0,"faction":0,"zone":0},{"_id":74,"traitName":"Tough","traitDesc":"","characterEffectId":122,"traitScore":1,"actionType":0,"resultType":0,"traitGroupId":12,"traitGroupId2":0,"muEvent1":0,"muEvent2":0,"muEx1":0,"muEx2":0,"muEx3":0,"muEx4":0,"muEx5":0,"muAdd1":0,"muAdd2":0,"muAdd3":0,"faction":0,"zone":0},{"_id":75,"traitName":"Loyal","traitDesc":"Committed to the ship, the captain and the crew, has only a 20% chance to abandon the ship due to low Morale","characterEffectId":0,"traitScore":1,"actionType":41,"resultType":0,"traitGroupId":12,"traitGroupId2":0,"muEvent1":0,"muEvent2":0,"muEx1":0,"muEx2":0,"muEx3":0,"muEx4":0,"muEx5":0,"muAdd1":0,"muAdd2":0,"muAdd3":0,"faction":0,"zone":0},{"_id":76,"traitName":"Confident","traitDesc":"","characterEffectId":123,"traitScore":1,"actionType":0,"resultType":0,"traitGroupId":12,"traitGroupId2":0,"muEvent1":0,"muEvent2":0,"muEx1":0,"muEx2":0,"muEx3":0,"muEx4":0,"muEx5":0,"muAdd1":0,"muAdd2":0,"muAdd3":0,"faction":0,"zone":0},{"_id":77,"traitName":"Bandit","traitDesc":"Frightening and overawing with threats, gain +10% profits on forcing other ships to give Tribute (max 30%)","characterEffectId":0,"traitScore":1,"actionType":85,"resultType":0,"traitGroupId":13,"traitGroupId2":0,"muEvent1":0,"muEvent2":0,"muEx1":0,"muEx2":0,"muEx3":0,"muEx4":0,"muEx5":0,"muAdd1":0,"muAdd2":0,"muAdd3":0,"faction":0,"zone":0},{"_id":78,"traitName":"Merciless","traitDesc":"Reveling in death and destruction, gain Morale whenever destroying enemy ship but lose Morale whenever ending combat in Draw or Ransom","characterEffectId":0,"traitScore":1,"actionType":86,"resultType":0,"traitGroupId":13,"traitGroupId2":0,"muEvent1":0,"muEvent2":0,"muEx1":0,"muEx2":0,"muEx3":0,"muEx4":0,"muEx5":0,"muAdd1":0,"muAdd2":0,"muAdd3":0,"faction":0,"zone":0},{"_id":79,"traitName":"Brute","traitDesc":"Penchant for taking out frustration on others, a loss in Morale causes an equal loss from another crew member","characterEffectId":153,"traitScore":-1,"actionType":61,"resultType":101,"traitGroupId":13,"traitGroupId2":0,"muEvent1":0,"muEvent2":0,"muEx1":0,"muEx2":0,"muEx3":0,"muEx4":0,"muEx5":0,"muAdd1":0,"muAdd2":0,"muAdd3":0,"faction":0,"zone":0},{"_id":80,"traitName":"Fearsome","traitDesc":"","characterEffectId":125,"traitScore":0,"actionType":0,"resultType":0,"traitGroupId":13,"traitGroupId2":0,"muEvent1":0,"muEvent2":0,"muEx1":0,"muEx2":0,"muEx3":0,"muEx4":0,"muEx5":0,"muAdd1":0,"muAdd2":0,"muAdd3":0,"faction":0,"zone":0},{"_id":81,"traitName":"Rash","traitDesc":"","characterEffectId":126,"traitScore":0,"actionType":0,"resultType":0,"traitGroupId":13,"traitGroupId2":0,"muEvent1":0,"muEvent2":0,"muEx1":0,"muEx2":0,"muEx3":0,"muEx4":0,"muEx5":0,"muAdd1":0,"muAdd2":0,"muAdd3":0,"faction":0,"zone":0},{"_id":82,"traitName":"Menacing","traitDesc":"20% chance to gain permanent +1 Intimidate Skill Bonus when leveling (max 12)","characterEffectId":0,"traitScore":2,"actionType":9,"resultType":0,"traitGroupId":13,"traitGroupId2":0,"muEvent1":0,"muEvent2":0,"muEx1":0,"muEx2":0,"muEx3":0,"muEx4":0,"muEx5":0,"muAdd1":0,"muAdd2":0,"muAdd3":0,"faction":0,"zone":0},{"_id":83,"traitName":"Berserk","traitDesc":"","characterEffectId":127,"traitScore":1,"actionType":0,"resultType":0,"traitGroupId":13,"traitGroupId2":0,"muEvent1":0,"muEvent2":0,"muEx1":0,"muEx2":0,"muEx3":0,"muEx4":0,"muEx5":0,"muAdd1":0,"muAdd2":0,"muAdd3":0,"faction":0,"zone":0},{"_id":84,"traitName":"Terrifying","traitDesc":"Scary in the worst way, confiscates 10% more Credits whenever successfully Blockading (max 30%)","characterEffectId":0,"traitScore":1,"actionType":58,"resultType":0,"traitGroupId":13,"traitGroupId2":0,"muEvent1":0,"muEvent2":0,"muEx1":0,"muEx2":0,"muEx3":0,"muEx4":0,"muEx5":0,"muAdd1":0,"muAdd2":0,"muAdd3":0,"faction":0,"zone":0},{"_id":85,"traitName":"Addictive Tic","traitDesc":"Increases chance that Trait mutation will result in other addiction-related Traits","characterEffectId":204,"traitScore":-1,"actionType":48,"resultType":0,"traitGroupId":14,"traitGroupId2":0,"muEvent1":0,"muEvent2":0,"muEx1":0,"muEx2":0,"muEx3":0,"muEx4":0,"muEx5":0,"muAdd1":0,"muAdd2":0,"muAdd3":0,"faction":0,"zone":0},{"_id":86,"traitName":"Drunk","traitDesc":"Only gains 50% Morale while at the Spice Hall","characterEffectId":0,"traitScore":-1,"actionType":0,"resultType":0,"traitGroupId":14,"traitGroupId2":0,"muEvent1":0,"muEvent2":0,"muEx1":0,"muEx2":0,"muEx3":0,"muEx4":0,"muEx5":0,"muAdd1":0,"muAdd2":0,"muAdd3":0,"faction":0,"zone":0},{"_id":87,"traitName":"Spice Addict","traitDesc":"Refuses anything but spice at the Spice Hall, requires more time and money","characterEffectId":0,"traitScore":-2,"actionType":0,"resultType":0,"traitGroupId":14,"traitGroupId2":0,"muEvent1":0,"muEvent2":0,"muEx1":0,"muEx2":0,"muEx3":0,"muEx4":0,"muEx5":0,"muAdd1":0,"muAdd2":0,"muAdd3":0,"faction":0,"zone":0},{"_id":88,"traitName":"Pain Tolerant","traitDesc":"","characterEffectId":128,"traitScore":1,"actionType":0,"resultType":0,"traitGroupId":14,"traitGroupId2":0,"muEvent1":0,"muEvent2":0,"muEx1":0,"muEx2":0,"muEx3":0,"muEx4":0,"muEx5":0,"muAdd1":0,"muAdd2":0,"muAdd3":0,"faction":0,"zone":0},{"_id":89,"traitName":"Greedy","traitDesc":"Pay Rate increases by $3 every level, gains extra Morale bonus whenever paid","characterEffectId":0,"traitScore":-1,"actionType":21,"resultType":3,"traitGroupId":14,"traitGroupId2":0,"muEvent1":0,"muEvent2":0,"muEx1":0,"muEx2":0,"muEx3":0,"muEx4":0,"muEx5":0,"muAdd1":0,"muAdd2":0,"muAdd3":0,"faction":0,"zone":0},{"_id":90,"traitName":"Obsessive","traitDesc":"Constantly fixating on something good or bad, double all negative or positive Morale changes","characterEffectId":154,"traitScore":1,"actionType":61,"resultType":101,"traitGroupId":14,"traitGroupId2":0,"muEvent1":0,"muEvent2":0,"muEx1":0,"muEx2":0,"muEx3":0,"muEx4":0,"muEx5":0,"muAdd1":0,"muAdd2":0,"muAdd3":0,"faction":0,"zone":0},{"_id":91,"traitName":"Battle Scarred","traitDesc":"","characterEffectId":129,"traitScore":0,"actionType":0,"resultType":0,"traitGroupId":15,"traitGroupId2":0,"muEvent1":0,"muEvent2":0,"muEx1":0,"muEx2":0,"muEx3":0,"muEx4":0,"muEx5":0,"muAdd1":0,"muAdd2":0,"muAdd3":0,"faction":0,"zone":0},{"_id":92,"traitName":"Crippled","traitDesc":"","characterEffectId":130,"traitScore":-2,"actionType":0,"resultType":0,"traitGroupId":15,"traitGroupId2":0,"muEvent1":0,"muEvent2":0,"muEx1":0,"muEx2":0,"muEx3":0,"muEx4":0,"muEx5":0,"muAdd1":0,"muAdd2":0,"muAdd3":0,"faction":0,"zone":0},{"_id":93,"traitName":"Revenant","traitDesc":"Death cannot break pure will, gains ability to survive even after failing Death Save; once Revenant has prevented a death it is removed","characterEffectId":0,"traitScore":2,"actionType":0,"resultType":0,"traitGroupId":15,"traitGroupId2":0,"muEvent1":0,"muEvent2":0,"muEx1":0,"muEx2":0,"muEx3":0,"muEx4":0,"muEx5":0,"muAdd1":0,"muAdd2":0,"muAdd3":0,"faction":0,"zone":0},{"_id":94,"traitName":"Death Wish","traitDesc":"Going out in a blaze of glory, -25% Death Save to survive lethal hit in any situation","characterEffectId":131,"traitScore":0,"actionType":0,"resultType":0,"traitGroupId":15,"traitGroupId2":0,"muEvent1":0,"muEvent2":0,"muEx1":0,"muEx2":0,"muEx3":0,"muEx4":0,"muEx5":0,"muAdd1":0,"muAdd2":0,"muAdd3":0,"faction":0,"zone":0},{"_id":95,"traitName":"Flashbacks","traitDesc":"Vivid and disturbing memories of past trauma cause paralysis, always 25% Stunned in Crew Combat","characterEffectId":225,"traitScore":-2,"actionType":27,"resultType":0,"traitGroupId":15,"traitGroupId2":0,"muEvent1":0,"muEvent2":0,"muEx1":0,"muEx2":0,"muEx3":0,"muEx4":0,"muEx5":0,"muAdd1":0,"muAdd2":0,"muAdd3":0,"faction":0,"zone":0},{"_id":96,"traitName":"Combat Nerves","traitDesc":"","characterEffectId":132,"traitScore":-1,"actionType":0,"resultType":0,"traitGroupId":15,"traitGroupId2":0,"muEvent1":0,"muEvent2":0,"muEx1":0,"muEx2":0,"muEx3":0,"muEx4":0,"muEx5":0,"muAdd1":0,"muAdd2":0,"muAdd3":0,"faction":0,"zone":0},{"_id":97,"traitName":"Jaded","traitDesc":"Lacking any illusions, 50% chance of resisting any positive or negative Morale change","characterEffectId":176,"traitScore":0,"actionType":61,"resultType":0,"traitGroupId":15,"traitGroupId2":0,"muEvent1":0,"muEvent2":0,"muEx1":0,"muEx2":0,"muEx3":0,"muEx4":0,"muEx5":0,"muAdd1":0,"muAdd2":0,"muAdd3":0,"faction":0,"zone":0},{"_id":98,"traitName":"Rigidly Lawful","traitDesc":"25% chance to lose 2-4 Morale when spicing in the brazen carnival of a 6 or higher Spice Hall. Loses 2-4 Morale on successfully accessing a Black Market","characterEffectId":0,"traitScore":-1,"actionType":18,"resultType":0,"traitGroupId":16,"traitGroupId2":0,"muEvent1":0,"muEvent2":0,"muEx1":0,"muEx2":0,"muEx3":0,"muEx4":0,"muEx5":0,"muAdd1":0,"muAdd2":0,"muAdd3":0,"faction":0,"zone":0},{"_id":99,"traitName":"Righteous","traitDesc":"","characterEffectId":138,"traitScore":1,"actionType":0,"resultType":0,"traitGroupId":16,"traitGroupId2":0,"muEvent1":0,"muEvent2":0,"muEx1":0,"muEx2":0,"muEx3":0,"muEx4":0,"muEx5":0,"muAdd1":0,"muAdd2":0,"muAdd3":0,"faction":0,"zone":0},{"_id":100,"traitName":"Reveres Authority","traitDesc":"Always joins the Captain's side of a Mutiny","characterEffectId":0,"traitScore":1,"actionType":42,"resultType":0,"traitGroupId":16,"traitGroupId2":0,"muEvent1":0,"muEvent2":0,"muEx1":0,"muEx2":0,"muEx3":0,"muEx4":0,"muEx5":0,"muAdd1":0,"muAdd2":0,"muAdd3":0,"faction":0,"zone":0},{"_id":101,"traitName":"Driven","traitDesc":"Unshakable in resolve, Morale will never drop below 50","characterEffectId":155,"traitScore":3,"actionType":61,"resultType":101,"traitGroupId":16,"traitGroupId2":0,"muEvent1":0,"muEvent2":0,"muEx1":0,"muEx2":0,"muEx3":0,"muEx4":0,"muEx5":0,"muAdd1":0,"muAdd2":0,"muAdd3":0,"faction":0,"zone":0},{"_id":102,"traitName":"Assertive","traitDesc":"Commanding and convinced of own authority, gains a Charisma % chance to increase Reputation bonuses by 25% whenever on Patrol","characterEffectId":0,"traitScore":1,"actionType":56,"resultType":0,"traitGroupId":16,"traitGroupId2":0,"muEvent1":0,"muEvent2":0,"muEx1":0,"muEx2":0,"muEx3":0,"muEx4":0,"muEx5":0,"muAdd1":0,"muAdd2":0,"muAdd3":0,"faction":0,"zone":0},{"_id":103,"traitName":"Frail","traitDesc":"","characterEffectId":142,"traitScore":-1,"actionType":0,"resultType":0,"traitGroupId":17,"traitGroupId2":0,"muEvent1":0,"muEvent2":0,"muEx1":0,"muEx2":0,"muEx3":0,"muEx4":0,"muEx5":0,"muAdd1":0,"muAdd2":0,"muAdd3":0,"faction":0,"zone":0},{"_id":104,"traitName":"Erudite","traitDesc":"","characterEffectId":143,"traitScore":1,"actionType":0,"resultType":0,"traitGroupId":17,"traitGroupId2":0,"muEvent1":0,"muEvent2":0,"muEx1":0,"muEx2":0,"muEx3":0,"muEx4":0,"muEx5":0,"muAdd1":0,"muAdd2":0,"muAdd3":0,"faction":0,"zone":0},{"_id":105,"traitName":"Snob","traitDesc":"At times condescending to the point of being insulting, gains a 50% chance to cause Morale loss in other crew members when spending time in the Spice Hall","characterEffectId":0,"traitScore":-2,"actionType":18,"resultType":0,"traitGroupId":17,"traitGroupId2":0,"muEvent1":0,"muEvent2":0,"muEx1":0,"muEx2":0,"muEx3":0,"muEx4":0,"muEx5":0,"muAdd1":0,"muAdd2":0,"muAdd3":0,"faction":0,"zone":0},{"_id":106,"traitName":"Astute Timing","traitDesc":"","characterEffectId":145,"traitScore":1,"actionType":0,"resultType":0,"traitGroupId":17,"traitGroupId2":0,"muEvent1":0,"muEvent2":0,"muEx1":0,"muEx2":0,"muEx3":0,"muEx4":0,"muEx5":0,"muAdd1":0,"muAdd2":0,"muAdd3":0,"faction":0,"zone":0},{"_id":107,"traitName":"Brilliant","traitDesc":"Expansive and lightning fast mind leaps to conclusions and solutions, +50% chance of gaining double XP","characterEffectId":160,"traitScore":3,"actionType":62,"resultType":102,"traitGroupId":17,"traitGroupId2":0,"muEvent1":0,"muEvent2":0,"muEx1":0,"muEx2":0,"muEx3":0,"muEx4":0,"muEx5":0,"muAdd1":0,"muAdd2":0,"muAdd3":0,"faction":0,"zone":0},{"_id":108,"traitName":"Headstrong","traitDesc":"Resistant to new ideas","characterEffectId":144,"traitScore":-1,"actionType":0,"resultType":0,"traitGroupId":17,"traitGroupId2":0,"muEvent1":0,"muEvent2":0,"muEx1":0,"muEx2":0,"muEx3":0,"muEx4":0,"muEx5":0,"muAdd1":0,"muAdd2":0,"muAdd3":0,"faction":0,"zone":0},{"_id":109,"traitName":"Skeptic","traitDesc":"","characterEffectId":146,"traitScore":2,"actionType":0,"resultType":0,"traitGroupId":17,"traitGroupId2":0,"muEvent1":0,"muEvent2":0,"muEx1":0,"muEx2":0,"muEx3":0,"muEx4":0,"muEx5":0,"muAdd1":0,"muAdd2":0,"muAdd3":0,"faction":0,"zone":0},{"_id":110,"traitName":"Highbrow","traitDesc":"Pay Rate increases by $2 every level, suffers Morale penalty if paid as a Crew instead of Officer","characterEffectId":0,"traitScore":-1,"actionType":21,"resultType":2,"traitGroupId":17,"traitGroupId2":0,"muEvent1":0,"muEvent2":0,"muEx1":0,"muEx2":0,"muEx3":0,"muEx4":0,"muEx5":0,"muAdd1":0,"muAdd2":0,"muAdd3":0,"faction":0,"zone":0},{"_id":111,"traitName":"Hates Indies","traitDesc":"NOT IMPLEMENTED; ","characterEffectId":0,"traitScore":0,"actionType":0,"resultType":0,"traitGroupId":18,"traitGroupId2":0,"muEvent1":0,"muEvent2":0,"muEx1":0,"muEx2":0,"muEx3":0,"muEx4":0,"muEx5":0,"muAdd1":0,"muAdd2":0,"muAdd3":0,"faction":0,"zone":0},{"_id":112,"traitName":"Hates De Valtos","traitDesc":"NOT IMPLEMENTED; ","characterEffectId":0,"traitScore":0,"actionType":0,"resultType":0,"traitGroupId":18,"traitGroupId2":0,"muEvent1":0,"muEvent2":0,"muEx1":0,"muEx2":0,"muEx3":0,"muEx4":0,"muEx5":0,"muAdd1":0,"muAdd2":0,"muAdd3":0,"faction":0,"zone":0},{"_id":113,"traitName":"Hates Cadar","traitDesc":"NOT IMPLEMENTED; ","characterEffectId":0,"traitScore":0,"actionType":0,"resultType":0,"traitGroupId":18,"traitGroupId2":0,"muEvent1":0,"muEvent2":0,"muEx1":0,"muEx2":0,"muEx3":0,"muEx4":0,"muEx5":0,"muAdd1":0,"muAdd2":0,"muAdd3":0,"faction":0,"zone":0},{"_id":114,"traitName":"Hates Rychart","traitDesc":"NOT IMPLEMENTED; ","characterEffectId":0,"traitScore":0,"actionType":0,"resultType":0,"traitGroupId":18,"traitGroupId2":0,"muEvent1":0,"muEvent2":0,"muEx1":0,"muEx2":0,"muEx3":0,"muEx4":0,"muEx5":0,"muAdd1":0,"muAdd2":0,"muAdd3":0,"faction":0,"zone":0},{"_id":115,"traitName":"Hates Thulun","traitDesc":"NOT IMPLEMENTED; ","characterEffectId":0,"traitScore":0,"actionType":0,"resultType":0,"traitGroupId":18,"traitGroupId2":0,"muEvent1":0,"muEvent2":0,"muEx1":0,"muEx2":0,"muEx3":0,"muEx4":0,"muEx5":0,"muAdd1":0,"muAdd2":0,"muAdd3":0,"faction":0,"zone":0},{"_id":116,"traitName":"Hates Javat","traitDesc":"NOT IMPLEMENTED; ","characterEffectId":0,"traitScore":0,"actionType":0,"resultType":0,"traitGroupId":18,"traitGroupId2":0,"muEvent1":0,"muEvent2":0,"muEx1":0,"muEx2":0,"muEx3":0,"muEx4":0,"muEx5":0,"muAdd1":0,"muAdd2":0,"muAdd3":0,"faction":0,"zone":0},{"_id":117,"traitName":"Hates Steel Song","traitDesc":"NOT IMPLEMENTED; ","characterEffectId":0,"traitScore":0,"actionType":0,"resultType":0,"traitGroupId":18,"traitGroupId2":0,"muEvent1":0,"muEvent2":0,"muEx1":0,"muEx2":0,"muEx3":0,"muEx4":0,"muEx5":0,"muAdd1":0,"muAdd2":0,"muAdd3":0,"faction":0,"zone":0},{"_id":118,"traitName":"Hates Moklumnue","traitDesc":"NOT IMPLEMENTED; ","characterEffectId":0,"traitScore":0,"actionType":0,"resultType":0,"traitGroupId":18,"traitGroupId2":0,"muEvent1":0,"muEvent2":0,"muEx1":0,"muEx2":0,"muEx3":0,"muEx4":0,"muEx5":0,"muAdd1":0,"muAdd2":0,"muAdd3":0,"faction":0,"zone":0},{"_id":119,"traitName":"Hates Alta Mesa","traitDesc":"NOT IMPLEMENTED; ","characterEffectId":0,"traitScore":0,"actionType":0,"resultType":0,"traitGroupId":18,"traitGroupId2":0,"muEvent1":0,"muEvent2":0,"muEx1":0,"muEx2":0,"muEx3":0,"muEx4":0,"muEx5":0,"muAdd1":0,"muAdd2":0,"muAdd3":0,"faction":0,"zone":0},{"_id":120,"traitName":"Hates Zenrin","traitDesc":"NOT IMPLEMENTED; ","characterEffectId":0,"traitScore":0,"actionType":0,"resultType":0,"traitGroupId":18,"traitGroupId2":0,"muEvent1":0,"muEvent2":0,"muEx1":0,"muEx2":0,"muEx3":0,"muEx4":0,"muEx5":0,"muAdd1":0,"muAdd2":0,"muAdd3":0,"faction":0,"zone":0},{"_id":124,"traitName":"Loves Indies","traitDesc":"NOT IMPLEMENTED; ","characterEffectId":0,"traitScore":0,"actionType":0,"resultType":0,"traitGroupId":19,"traitGroupId2":0,"muEvent1":0,"muEvent2":0,"muEx1":0,"muEx2":0,"muEx3":0,"muEx4":0,"muEx5":0,"muAdd1":0,"muAdd2":0,"muAdd3":0,"faction":0,"zone":0},{"_id":125,"traitName":"Loves De Valtos","traitDesc":"NOT IMPLEMENTED; ","characterEffectId":0,"traitScore":0,"actionType":0,"resultType":0,"traitGroupId":19,"traitGroupId2":0,"muEvent1":0,"muEvent2":0,"muEx1":0,"muEx2":0,"muEx3":0,"muEx4":0,"muEx5":0,"muAdd1":0,"muAdd2":0,"muAdd3":0,"faction":0,"zone":0},{"_id":126,"traitName":"Loves Cadar","traitDesc":"NOT IMPLEMENTED; ","characterEffectId":0,"traitScore":0,"actionType":0,"resultType":0,"traitGroupId":19,"traitGroupId2":0,"muEvent1":0,"muEvent2":0,"muEx1":0,"muEx2":0,"muEx3":0,"muEx4":0,"muEx5":0,"muAdd1":0,"muAdd2":0,"muAdd3":0,"faction":0,"zone":0},{"_id":127,"traitName":"Loves Rychart","traitDesc":"NOT IMPLEMENTED; ","characterEffectId":0,"traitScore":0,"actionType":0,"resultType":0,"traitGroupId":19,"traitGroupId2":0,"muEvent1":0,"muEvent2":0,"muEx1":0,"muEx2":0,"muEx3":0,"muEx4":0,"muEx5":0,"muAdd1":0,"muAdd2":0,"muAdd3":0,"faction":0,"zone":0},{"_id":128,"traitName":"Loves Thulun","traitDesc":"NOT IMPLEMENTED; ","characterEffectId":0,"traitScore":0,"actionType":0,"resultType":0,"traitGroupId":19,"traitGroupId2":0,"muEvent1":0,"muEvent2":0,"muEx1":0,"muEx2":0,"muEx3":0,"muEx4":0,"muEx5":0,"muAdd1":0,"muAdd2":0,"muAdd3":0,"faction":0,"zone":0},{"_id":129,"traitName":"Loves Javat","traitDesc":"NOT IMPLEMENTED; ","characterEffectId":0,"traitScore":0,"actionType":0,"resultType":0,"traitGroupId":19,"traitGroupId2":0,"muEvent1":0,"muEvent2":0,"muEx1":0,"muEx2":0,"muEx3":0,"muEx4":0,"muEx5":0,"muAdd1":0,"muAdd2":0,"muAdd3":0,"faction":0,"zone":0},{"_id":130,"traitName":"Loves Steel Song","traitDesc":"NOT IMPLEMENTED; ","characterEffectId":0,"traitScore":0,"actionType":0,"resultType":0,"traitGroupId":19,"traitGroupId2":0,"muEvent1":0,"muEvent2":0,"muEx1":0,"muEx2":0,"muEx3":0,"muEx4":0,"muEx5":0,"muAdd1":0,"muAdd2":0,"muAdd3":0,"faction":0,"zone":0},{"_id":131,"traitName":"Loves Moklumnue","traitDesc":"NOT IMPLEMENTED; ","characterEffectId":0,"traitScore":0,"actionType":0,"resultType":0,"traitGroupId":19,"traitGroupId2":0,"muEvent1":0,"muEvent2":0,"muEx1":0,"muEx2":0,"muEx3":0,"muEx4":0,"muEx5":0,"muAdd1":0,"muAdd2":0,"muAdd3":0,"faction":0,"zone":0},{"_id":132,"traitName":"Loves Alta Mesa","traitDesc":"NOT IMPLEMENTED; ","characterEffectId":0,"traitScore":0,"actionType":0,"resultType":0,"traitGroupId":19,"traitGroupId2":0,"muEvent1":0,"muEvent2":0,"muEx1":0,"muEx2":0,"muEx3":0,"muEx4":0,"muEx5":0,"muAdd1":0,"muAdd2":0,"muAdd3":0,"faction":0,"zone":0},{"_id":133,"traitName":"Loves Zenrin","traitDesc":"NOT IMPLEMENTED; ","characterEffectId":0,"traitScore":0,"actionType":0,"resultType":0,"traitGroupId":19,"traitGroupId2":0,"muEvent1":0,"muEvent2":0,"muEx1":0,"muEx2":0,"muEx3":0,"muEx4":0,"muEx5":0,"muAdd1":0,"muAdd2":0,"muAdd3":0,"faction":0,"zone":0},{"_id":137,"traitName":"Life-Spark","traitDesc":"+25% Chance to Survive death in crew combat (still removed from battle)","characterEffectId":0,"traitScore":1,"actionType":49,"resultType":0,"traitGroupId":6,"traitGroupId2":0,"muEvent1":0,"muEvent2":0,"muEx1":0,"muEx2":0,"muEx3":0,"muEx4":0,"muEx5":0,"muAdd1":0,"muAdd2":0,"muAdd3":0,"faction":0,"zone":0},{"_id":138,"traitName":"Survivor","traitDesc":"+50% Death Save to Survive lethal hit in any situation","characterEffectId":0,"traitScore":2,"actionType":49,"resultType":0,"traitGroupId":3,"traitGroupId2":0,"muEvent1":0,"muEvent2":0,"muEx1":0,"muEx2":0,"muEx3":0,"muEx4":0,"muEx5":0,"muAdd1":0,"muAdd2":0,"muAdd3":0,"faction":0,"zone":0},{"_id":139,"traitName":"Malcontent","traitDesc":"Always rises against the Captain in a Mutiny","characterEffectId":0,"traitScore":-1,"actionType":42,"resultType":0,"traitGroupId":3,"traitGroupId2":0,"muEvent1":0,"muEvent2":0,"muEx1":0,"muEx2":0,"muEx3":0,"muEx4":0,"muEx5":0,"muAdd1":0,"muAdd2":0,"muAdd3":0,"faction":0,"zone":0},{"_id":140,"traitName":"Lucky","traitDesc":"+25% Death Save to Survive lethal hit in any situation; has a chance of wearing off after each use","characterEffectId":0,"traitScore":1,"actionType":49,"resultType":0,"traitGroupId":6,"traitGroupId2":0,"muEvent1":0,"muEvent2":0,"muEx1":0,"muEx2":0,"muEx3":0,"muEx4":0,"muEx5":0,"muAdd1":0,"muAdd2":0,"muAdd3":0,"faction":0,"zone":0},{"_id":141,"traitName":"Calculating","traitDesc":"20% chance to gain permanent +1 Tactics Skill Bonus when leveling (max 12)","characterEffectId":1145,"traitScore":2,"actionType":5,"resultType":0,"traitGroupId":9,"traitGroupId2":0,"muEvent1":0,"muEvent2":0,"muEx1":0,"muEx2":0,"muEx3":0,"muEx4":0,"muEx5":0,"muAdd1":0,"muAdd2":0,"muAdd3":0,"faction":0,"zone":0},{"_id":142,"traitName":"Problem Solver","traitDesc":"20% chance to gain permanent +1 Electronics Skill Bonus when leveling (max 12)","characterEffectId":0,"traitScore":2,"actionType":3,"resultType":0,"traitGroupId":17,"traitGroupId2":0,"muEvent1":0,"muEvent2":0,"muEx1":0,"muEx2":0,"muEx3":0,"muEx4":0,"muEx5":0,"muAdd1":0,"muAdd2":0,"muAdd3":0,"faction":0,"zone":0},{"_id":143,"traitName":"Intrepid","traitDesc":"20% chance to gain permanent +1 Explore Skill Bonus when leveling (max 12)","characterEffectId":0,"traitScore":2,"actionType":26,"resultType":0,"traitGroupId":12,"traitGroupId2":0,"muEvent1":0,"muEvent2":0,"muEx1":0,"muEx2":0,"muEx3":0,"muEx4":0,"muEx5":0,"muAdd1":0,"muAdd2":0,"muAdd3":0,"faction":0,"zone":0},{"_id":144,"traitName":"Neverlost","traitDesc":"20% chance to gain permanent +1 Navigation Skill Bonus when leveling (max 12)","characterEffectId":0,"traitScore":2,"actionType":4,"resultType":0,"traitGroupId":4,"traitGroupId2":0,"muEvent1":0,"muEvent2":0,"muEx1":0,"muEx2":0,"muEx3":0,"muEx4":0,"muEx5":0,"muAdd1":0,"muAdd2":0,"muAdd3":0,"faction":0,"zone":0},{"_id":145,"traitName":"Fatalistic","traitDesc":"Seeing death as inevitable in the end, -10% Death Save to Survive lethal hit in any situation","characterEffectId":0,"traitScore":-1,"actionType":49,"resultType":0,"traitGroupId":14,"traitGroupId2":0,"muEvent1":0,"muEvent2":0,"muEx1":0,"muEx2":0,"muEx3":0,"muEx4":0,"muEx5":0,"muAdd1":0,"muAdd2":0,"muAdd3":0,"faction":0,"zone":0},{"_id":146,"traitName":"Weak System","traitDesc":"","characterEffectId":200,"traitScore":-1,"actionType":0,"resultType":0,"traitGroupId":15,"traitGroupId2":0,"muEvent1":0,"muEvent2":0,"muEx1":0,"muEx2":0,"muEx3":0,"muEx4":0,"muEx5":0,"muAdd1":0,"muAdd2":0,"muAdd3":0,"faction":0,"zone":0},{"_id":147,"traitName":"Mindful","traitDesc":"","characterEffectId":124,"traitScore":1,"actionType":0,"resultType":0,"traitGroupId":17,"traitGroupId2":0,"muEvent1":0,"muEvent2":0,"muEx1":0,"muEx2":0,"muEx3":0,"muEx4":0,"muEx5":0,"muAdd1":0,"muAdd2":0,"muAdd3":0,"faction":0,"zone":0},{"_id":148,"traitName":"Meticulous Care","traitDesc":"20% chance to gain permanent +1 Doctor Skill Bonus when leveling (max 12)","characterEffectId":0,"traitScore":2,"actionType":8,"resultType":0,"traitGroupId":17,"traitGroupId2":0,"muEvent1":0,"muEvent2":0,"muEx1":0,"muEx2":0,"muEx3":0,"muEx4":0,"muEx5":0,"muAdd1":0,"muAdd2":0,"muAdd3":0,"faction":0,"zone":0},{"_id":149,"traitName":"Sturdy","traitDesc":"","characterEffectId":201,"traitScore":2,"actionType":0,"resultType":0,"traitGroupId":12,"traitGroupId2":0,"muEvent1":0,"muEvent2":0,"muEx1":0,"muEx2":0,"muEx3":0,"muEx4":0,"muEx5":0,"muAdd1":0,"muAdd2":0,"muAdd3":0,"faction":0,"zone":0},{"_id":150,"traitName":"Libertine","traitDesc":"Freewheeling and loved for leading the party, increases Morale bonus in Spice Hall when Trade Law is less than 5","characterEffectId":0,"traitScore":1,"actionType":18,"resultType":0,"traitGroupId":8,"traitGroupId2":0,"muEvent1":0,"muEvent2":0,"muEx1":0,"muEx2":0,"muEx3":0,"muEx4":0,"muEx5":0,"muAdd1":0,"muAdd2":0,"muAdd3":0,"faction":0,"zone":0},{"_id":151,"traitName":"Spiritual","traitDesc":"Seeing past worldly turmoil leads to inner zen, reduces Morale loss by 25%","characterEffectId":202,"traitScore":2,"actionType":0,"resultType":0,"traitGroupId":6,"traitGroupId2":0,"muEvent1":0,"muEvent2":0,"muEx1":0,"muEx2":0,"muEx3":0,"muEx4":0,"muEx5":0,"muAdd1":0,"muAdd2":0,"muAdd3":0,"faction":0,"zone":0},{"_id":152,"traitName":"Power Hungry","traitDesc":"Always rises against the Captain in a Mutiny","characterEffectId":203,"traitScore":0,"actionType":42,"resultType":0,"traitGroupId":13,"traitGroupId2":0,"muEvent1":0,"muEvent2":0,"muEx1":0,"muEx2":0,"muEx3":0,"muEx4":0,"muEx5":0,"muAdd1":0,"muAdd2":0,"muAdd3":0,"faction":0,"zone":0},{"_id":153,"traitName":"Nimble","traitDesc":"20% chance to gain permanent +1 Evasion Skill Bonus when leveling (max 8)","characterEffectId":1146,"traitScore":2,"actionType":98,"resultType":0,"traitGroupId":10,"traitGroupId2":0,"muEvent1":0,"muEvent2":0,"muEx1":0,"muEx2":0,"muEx3":0,"muEx4":0,"muEx5":0,"muAdd1":0,"muAdd2":0,"muAdd3":0,"faction":0,"zone":0},{"_id":154,"traitName":"Principled","traitDesc":"Upstanding and stern in peaceful ransom, gain +10% profits on Ransoming enemy ship","characterEffectId":0,"traitScore":1,"actionType":87,"resultType":0,"traitGroupId":7,"traitGroupId2":0,"muEvent1":0,"muEvent2":0,"muEx1":0,"muEx2":0,"muEx3":0,"muEx4":0,"muEx5":0,"muAdd1":0,"muAdd2":0,"muAdd3":0,"faction":0,"zone":0},{"_id":155,"traitName":"DE VALTOS","traitDesc":"","characterEffectId":0,"traitScore":2,"actionType":0,"resultType":0,"traitGroupId":21,"traitGroupId2":0,"muEvent1":0,"muEvent2":0,"muEx1":0,"muEx2":0,"muEx3":0,"muEx4":0,"muEx5":0,"muAdd1":0,"muAdd2":0,"muAdd3":0,"faction":0,"zone":0},{"_id":156,"traitName":"CADAR","traitDesc":"","characterEffectId":0,"traitScore":2,"actionType":0,"resultType":0,"traitGroupId":21,"traitGroupId2":0,"muEvent1":0,"muEvent2":0,"muEx1":0,"muEx2":0,"muEx3":0,"muEx4":0,"muEx5":0,"muAdd1":0,"muAdd2":0,"muAdd3":0,"faction":0,"zone":0},{"_id":157,"traitName":"RYCHART","traitDesc":"","characterEffectId":0,"traitScore":2,"actionType":0,"resultType":0,"traitGroupId":21,"traitGroupId2":0,"muEvent1":0,"muEvent2":0,"muEx1":0,"muEx2":0,"muEx3":0,"muEx4":0,"muEx5":0,"muAdd1":0,"muAdd2":0,"muAdd3":0,"faction":0,"zone":0},{"_id":158,"traitName":"THULUN","traitDesc":"","characterEffectId":0,"traitScore":2,"actionType":0,"resultType":0,"traitGroupId":21,"traitGroupId2":0,"muEvent1":0,"muEvent2":0,"muEx1":0,"muEx2":0,"muEx3":0,"muEx4":0,"muEx5":0,"muAdd1":0,"muAdd2":0,"muAdd3":0,"faction":0,"zone":0},{"_id":159,"traitName":"JAVAT","traitDesc":"","characterEffectId":0,"traitScore":2,"actionType":0,"resultType":0,"traitGroupId":21,"traitGroupId2":0,"muEvent1":0,"muEvent2":0,"muEx1":0,"muEx2":0,"muEx3":0,"muEx4":0,"muEx5":0,"muAdd1":0,"muAdd2":0,"muAdd3":0,"faction":0,"zone":0},{"_id":160,"traitName":"STEEL SONG","traitDesc":"","characterEffectId":0,"traitScore":2,"actionType":0,"resultType":0,"traitGroupId":21,"traitGroupId2":0,"muEvent1":0,"muEvent2":0,"muEx1":0,"muEx2":0,"muEx3":0,"muEx4":0,"muEx5":0,"muAdd1":0,"muAdd2":0,"muAdd3":0,"faction":0,"zone":0},{"_id":161,"traitName":"MOKLUMNUE","traitDesc":"","characterEffectId":0,"traitScore":2,"actionType":0,"resultType":0,"traitGroupId":21,"traitGroupId2":0,"muEvent1":0,"muEvent2":0,"muEx1":0,"muEx2":0,"muEx3":0,"muEx4":0,"muEx5":0,"muAdd1":0,"muAdd2":0,"muAdd3":0,"faction":0,"zone":0},{"_id":162,"traitName":"ALTA MESA","traitDesc":"","characterEffectId":0,"traitScore":2,"actionType":0,"resultType":0,"traitGroupId":21,"traitGroupId2":0,"muEvent1":0,"muEvent2":0,"muEx1":0,"muEx2":0,"muEx3":0,"muEx4":0,"muEx5":0,"muAdd1":0,"muAdd2":0,"muAdd3":0,"faction":0,"zone":0},{"_id":163,"traitName":"ZENRIN","traitDesc":"","characterEffectId":0,"traitScore":2,"actionType":0,"resultType":0,"traitGroupId":21,"traitGroupId2":0,"muEvent1":0,"muEvent2":0,"muEx1":0,"muEx2":0,"muEx3":0,"muEx4":0,"muEx5":0,"muAdd1":0,"muAdd2":0,"muAdd3":0,"faction":0,"zone":0},{"_id":164,"traitName":"Relentless","traitDesc":"Dogged in the pursuit, completing any mission step that requires an Edict grants +10% payment, extra Rep and a personal XP bonus","characterEffectId":0,"traitScore":3,"actionType":0,"resultType":0,"traitGroupId":22,"traitGroupId2":0,"muEvent1":0,"muEvent2":0,"muEx1":0,"muEx2":0,"muEx3":0,"muEx4":0,"muEx5":0,"muAdd1":0,"muAdd2":0,"muAdd3":0,"faction":0,"zone":0},{"_id":165,"traitName":"Born Hunter","traitDesc":"A natural predator, +2 Resilience, +10% All Accuracy, +2 Initiative","characterEffectId":232,"traitScore":3,"actionType":0,"resultType":0,"traitGroupId":22,"traitGroupId2":0,"muEvent1":0,"muEvent2":0,"muEx1":0,"muEx2":0,"muEx3":0,"muEx4":0,"muEx5":0,"muAdd1":0,"muAdd2":0,"muAdd3":0,"faction":0,"zone":0},{"_id":166,"traitName":"Overkeen","traitDesc":"Obsessive in the search, double the chance of drawing Xeno Artifact cards while Exploring and Exploring Missions start with +10% chance to draw Mission card","characterEffectId":0,"traitScore":3,"actionType":0,"resultType":0,"traitGroupId":22,"traitGroupId2":0,"muEvent1":0,"muEvent2":0,"muEx1":0,"muEx2":0,"muEx3":0,"muEx4":0,"muEx5":0,"muAdd1":0,"muAdd2":0,"muAdd3":0,"faction":0,"zone":0},{"_id":167,"traitName":"Voyager","traitDesc":"Highly skilled at riding the galactic winds, +2 Wisdom, +1 Resilience and reduces travel time and fuel consumption by 10%","characterEffectId":237,"traitScore":3,"actionType":0,"resultType":0,"traitGroupId":22,"traitGroupId2":0,"muEvent1":0,"muEvent2":0,"muEx1":0,"muEx2":0,"muEx3":0,"muEx4":0,"muEx5":0,"muAdd1":0,"muAdd2":0,"muAdd3":0,"faction":0,"zone":0},{"_id":168,"traitName":"Exacting","traitDesc":"Well-versed in every aspect of the trade, +2 Charisma, +1 Wisdom and gains +10% profit when trading at an Exchange","characterEffectId":229,"traitScore":3,"actionType":0,"resultType":0,"traitGroupId":22,"traitGroupId2":0,"muEvent1":0,"muEvent2":0,"muEx1":0,"muEx2":0,"muEx3":0,"muEx4":0,"muEx5":0,"muAdd1":0,"muAdd2":0,"muAdd3":0,"faction":0,"zone":0},{"_id":169,"traitName":"Lawful","traitDesc":"Known for legitimate dealings, reduces the hostility of law-abiding ships (Military Officers, Merchants, Bounty Hunters, Zealots) encountered in travel by 1","characterEffectId":0,"traitScore":3,"actionType":0,"resultType":0,"traitGroupId":22,"traitGroupId2":0,"muEvent1":0,"muEvent2":0,"muEx1":0,"muEx2":0,"muEx3":0,"muEx4":0,"muEx5":0,"muAdd1":0,"muAdd2":0,"muAdd3":0,"faction":0,"zone":0},{"_id":170,"traitName":"Protector","traitDesc":"A faction soldier, any Orbital Ops card that adds Rep gains +2-4 bonus and Blockade or Patrol Missions start with +10% chance to draw Mission card","characterEffectId":0,"traitScore":3,"actionType":0,"resultType":0,"traitGroupId":22,"traitGroupId2":0,"muEvent1":0,"muEvent2":0,"muEx1":0,"muEx2":0,"muEx3":0,"muEx4":0,"muEx5":0,"muAdd1":0,"muAdd2":0,"muAdd3":0,"faction":0,"zone":0},{"_id":171,"traitName":"Conditioned","traitDesc":"Hardened by military training, +1 Quickness, +2 Fortitude, +10% Armor, +10% All Accuracy","characterEffectId":233,"traitScore":3,"actionType":0,"resultType":0,"traitGroupId":22,"traitGroupId2":0,"muEvent1":0,"muEvent2":0,"muEx1":0,"muEx2":0,"muEx3":0,"muEx4":0,"muEx5":0,"muAdd1":0,"muAdd2":0,"muAdd3":0,"faction":0,"zone":0},{"_id":172,"traitName":"Uncompromising","traitDesc":"Demanding ferocity brooks no argument, +2 Resilience, +1 Fortitude and doubles all Credits extorted from enemy captains in Blockade or Ship Encounter","characterEffectId":227,"traitScore":3,"actionType":0,"resultType":0,"traitGroupId":22,"traitGroupId2":0,"muEvent1":0,"muEvent2":0,"muEx1":0,"muEx2":0,"muEx3":0,"muEx4":0,"muEx5":0,"muAdd1":0,"muAdd2":0,"muAdd3":0,"faction":0,"zone":0},{"_id":173,"traitName":"Marauder","traitDesc":"Eager to hunt profit, gains +10 Boarding, +10% Accuracy, +5 Range Change in Ship Combat","characterEffectId":-90,"traitScore":3,"actionType":0,"resultType":0,"traitGroupId":22,"traitGroupId2":0,"muEvent1":0,"muEvent2":0,"muEx1":0,"muEx2":0,"muEx3":0,"muEx4":0,"muEx5":0,"muAdd1":0,"muAdd2":0,"muAdd3":0,"faction":0,"zone":0},{"_id":174,"traitName":"Exploiter","traitDesc":"Leveraging the risk required to avoid trade law, +1 Quickness, +2 Charisma and gains +10% profit when trading at a Black Market","characterEffectId":228,"traitScore":3,"actionType":0,"resultType":0,"traitGroupId":22,"traitGroupId2":0,"muEvent1":0,"muEvent2":0,"muEx1":0,"muEx2":0,"muEx3":0,"muEx4":0,"muEx5":0,"muAdd1":0,"muAdd2":0,"muAdd3":0,"faction":0,"zone":0},{"_id":175,"traitName":"Flighty","traitDesc":"Always dodging the law, gains +5 Escape, +10% Defense, +5% Shield in Ship Combat","characterEffectId":-91,"traitScore":3,"actionType":0,"resultType":0,"traitGroupId":22,"traitGroupId2":0,"muEvent1":0,"muEvent2":0,"muEx1":0,"muEx2":0,"muEx3":0,"muEx4":0,"muEx5":0,"muAdd1":0,"muAdd2":0,"muAdd3":0,"faction":0,"zone":0},{"_id":176,"traitName":"Infiltrator","traitDesc":"Intergalactic character of mystery, +2 Wisdom, +1 Charisma and gains +15% profit when selling Conflict Intel to one of the involved factions","characterEffectId":226,"traitScore":3,"actionType":0,"resultType":0,"traitGroupId":22,"traitGroupId2":0,"muEvent1":0,"muEvent2":0,"muEx1":0,"muEx2":0,"muEx3":0,"muEx4":0,"muEx5":0,"muAdd1":0,"muAdd2":0,"muAdd3":0,"faction":0,"zone":0},{"_id":177,"traitName":"Slippery","traitDesc":"Either about to disappear or backstab, gains +5 Escape, +5% Shield, +10% Critical in Ship Combat","characterEffectId":-92,"traitScore":3,"actionType":0,"resultType":0,"traitGroupId":22,"traitGroupId2":0,"muEvent1":0,"muEvent2":0,"muEx1":0,"muEx2":0,"muEx3":0,"muEx4":0,"muEx5":0,"muAdd1":0,"muAdd2":0,"muAdd3":0,"faction":0,"zone":0},{"_id":178,"traitName":"Warhawk","traitDesc":"Antagonistic faction supporter, gains extra +3-4 Conflict Score and a personal XP bonus whenever impacting a Conflict","characterEffectId":0,"traitScore":3,"actionType":0,"resultType":0,"traitGroupId":22,"traitGroupId2":0,"muEvent1":0,"muEvent2":0,"muEx1":0,"muEx2":0,"muEx3":0,"muEx4":0,"muEx5":0,"muAdd1":0,"muAdd2":0,"muAdd3":0,"faction":0,"zone":0},{"_id":179,"traitName":"Single-Minded","traitDesc":"Diehard and inflexible, +2 Resilience, +2 Initiative, +10% All Damage, Morale never breaks in Crew Combat ","characterEffectId":231,"traitScore":3,"actionType":0,"resultType":0,"traitGroupId":22,"traitGroupId2":0,"muEvent1":0,"muEvent2":0,"muEx1":0,"muEx2":0,"muEx3":0,"muEx4":0,"muEx5":0,"muAdd1":0,"muAdd2":0,"muAdd3":0,"faction":0,"zone":0},{"_id":180,"traitName":"Pox Infected","traitDesc":"Infected crew are contagious and may spread the Crimson Pox to faction landing zones","characterEffectId":221,"traitScore":-2,"actionType":15,"resultType":0,"traitGroupId":23,"traitGroupId2":0,"muEvent1":0,"muEvent2":0,"muEx1":0,"muEx2":0,"muEx3":0,"muEx4":0,"muEx5":0,"muAdd1":0,"muAdd2":0,"muAdd3":0,"faction":0,"zone":0},{"_id":181,"traitName":"Plague Scarred","traitDesc":"Scarred by the crimson pox","characterEffectId":222,"traitScore":0,"actionType":0,"resultType":0,"traitGroupId":23,"traitGroupId2":0,"muEvent1":0,"muEvent2":0,"muEx1":0,"muEx2":0,"muEx3":0,"muEx4":0,"muEx5":0,"muAdd1":0,"muAdd2":0,"muAdd3":0,"faction":0,"zone":0},{"_id":182,"traitName":"Pox Survivor","traitDesc":"Crimson pox survivor","characterEffectId":223,"traitScore":1,"actionType":0,"resultType":0,"traitGroupId":23,"traitGroupId2":0,"muEvent1":0,"muEvent2":0,"muEx1":0,"muEx2":0,"muEx3":0,"muEx4":0,"muEx5":0,"muAdd1":0,"muAdd2":0,"muAdd3":0,"faction":0,"zone":0},{"_id":183,"traitName":"Resilient System","traitDesc":"Having survived worse, all Morale loss is reduced by 50%","characterEffectId":224,"traitScore":2,"actionType":0,"resultType":0,"traitGroupId":23,"traitGroupId2":0,"muEvent1":0,"muEvent2":0,"muEx1":0,"muEx2":0,"muEx3":0,"muEx4":0,"muEx5":0,"muAdd1":0,"muAdd2":0,"muAdd3":0,"faction":0,"zone":0},{"_id":184,"traitName":"Hazard High","traitDesc":"Thrilled by the high-stakes risks, gains a Resilience % chance to recover 5 to 8 Morale whenever Salvaging at an Orbital","characterEffectId":0,"traitScore":1,"actionType":102,"resultType":0,"traitGroupId":4,"traitGroupId2":0,"muEvent1":0,"muEvent2":0,"muEx1":0,"muEx2":0,"muEx3":0,"muEx4":0,"muEx5":0,"muAdd1":0,"muAdd2":0,"muAdd3":0,"faction":0,"zone":0},{"_id":185,"traitName":"Crafty","traitDesc":"Good at spotting hiding spots, grants +10% cargo rewards whenever Salvaging an orbital (max 30%)","characterEffectId":0,"traitScore":2,"actionType":102,"resultType":0,"traitGroupId":4,"traitGroupId2":0,"muEvent1":0,"muEvent2":0,"muEx1":0,"muEx2":0,"muEx3":0,"muEx4":0,"muEx5":0,"muAdd1":0,"muAdd2":0,"muAdd3":0,"faction":0,"zone":0},{"_id":186,"traitName":"Junker","traitDesc":"All scrap has a use, fixes 2 ship components up to Repair Skill whenever salvaging a destroyed ship or drawing a Salvage card that grants Credits and Salvage Missions start with +10% chance to draw Mission card","characterEffectId":0,"traitScore":3,"actionType":0,"resultType":0,"traitGroupId":22,"traitGroupId2":0,"muEvent1":0,"muEvent2":0,"muEx1":0,"muEx2":0,"muEx3":0,"muEx4":0,"muEx5":0,"muAdd1":0,"muAdd2":0,"muAdd3":0,"faction":0,"zone":0},{"_id":187,"traitName":"Roughneck","traitDesc":"Rough but durable and approachable, +2 Fortitude, +2 Wisdom and gains 10% chance to learn a Salvage Rumor when Spicing","characterEffectId":239,"traitScore":3,"actionType":18,"resultType":0,"traitGroupId":22,"traitGroupId2":0,"muEvent1":0,"muEvent2":0,"muEx1":0,"muEx2":0,"muEx3":0,"muEx4":0,"muEx5":0,"muAdd1":0,"muAdd2":0,"muAdd3":0,"faction":0,"zone":0},{"_id":188,"traitName":"Honorable","traitDesc":"Reputable and trustworthy, adds +1-2 bonus Personal and faction Rep whenever completing a Mission step and reduces negative Rep by 1","characterEffectId":0,"traitScore":3,"actionType":0,"resultType":0,"traitGroupId":22,"traitGroupId2":0,"muEvent1":0,"muEvent2":0,"muEx1":0,"muEx2":0,"muEx3":0,"muEx4":0,"muEx5":0,"muAdd1":0,"muAdd2":0,"muAdd3":0,"faction":0,"zone":0},{"_id":189,"traitName":"Smooth","traitDesc":"Utterly practiced at the art of persuasion, +3 Charisma, +2 Wisdom and reduces cost of Contact Introduction by 15% while granting a +20 Personal Rep bonus","characterEffectId":238,"traitScore":3,"actionType":0,"resultType":0,"traitGroupId":22,"traitGroupId2":0,"muEvent1":0,"muEvent2":0,"muEx1":0,"muEx2":0,"muEx3":0,"muEx4":0,"muEx5":0,"muAdd1":0,"muAdd2":0,"muAdd3":0,"faction":0,"zone":0},{"_id":190,"traitName":"Stalker","traitDesc":"Seeks high-value targets, when crew combat includes an enemy officer or captain then immediately gains a Buff for +15% Critical, +10% Dodge, +10% Parry and Stealth Mode for 3 Turns","characterEffectId":0,"traitScore":3,"actionType":0,"resultType":0,"traitGroupId":22,"traitGroupId2":0,"muEvent1":0,"muEvent2":0,"muEx1":0,"muEx2":0,"muEx3":0,"muEx4":0,"muEx5":0,"muAdd1":0,"muAdd2":0,"muAdd3":0,"faction":0,"zone":0},{"_id":191,"traitName":"On Edge","traitDesc":"Coiled spring ready to strike, +1 Strength, +1 Fortitude, +3 Initiative","characterEffectId":230,"traitScore":3,"actionType":0,"resultType":0,"traitGroupId":22,"traitGroupId2":0,"muEvent1":0,"muEvent2":0,"muEx1":0,"muEx2":0,"muEx3":0,"muEx4":0,"muEx5":0,"muAdd1":0,"muAdd2":0,"muAdd3":0,"faction":0,"zone":0},{"_id":192,"traitName":"Indomitable","traitDesc":"Defeat is unimaginable, gains +10% Accuracy, +5% Defense, +10% Protection against Crew and Morale Dmg/Turn in Ship Combat","characterEffectId":-95,"traitScore":3,"actionType":0,"resultType":0,"traitGroupId":22,"traitGroupId2":0,"muEvent1":0,"muEvent2":0,"muEx1":0,"muEx2":0,"muEx3":0,"muEx4":0,"muEx5":0,"muAdd1":0,"muAdd2":0,"muAdd3":0,"faction":0,"zone":0},{"_id":193,"traitName":"Motivating","traitDesc":"Stirring words and powerful presence, gains +2 Charisma, +2 Wisdom, +1 Initiative, +20% Debuff Resist","characterEffectId":236,"traitScore":3,"actionType":0,"resultType":0,"traitGroupId":22,"traitGroupId2":0,"muEvent1":0,"muEvent2":0,"muEx1":0,"muEx2":0,"muEx3":0,"muEx4":0,"muEx5":0,"muAdd1":0,"muAdd2":0,"muAdd3":0,"faction":0,"zone":0},{"_id":194,"traitName":"Fierce","traitDesc":"","characterEffectId":240,"traitScore":1,"actionType":0,"resultType":0,"traitGroupId":13,"traitGroupId2":0,"muEvent1":0,"muEvent2":0,"muEx1":0,"muEx2":0,"muEx3":0,"muEx4":0,"muEx5":0,"muAdd1":0,"muAdd2":0,"muAdd3":0,"faction":0,"zone":0},{"_id":195,"traitName":"Hypochondriac","traitDesc":"Constantly worried about unknown medical maladies, healing costs twice as much as usual","characterEffectId":0,"traitScore":-1,"actionType":0,"resultType":0,"traitGroupId":13,"traitGroupId2":0,"muEvent1":0,"muEvent2":0,"muEx1":0,"muEx2":0,"muEx3":0,"muEx4":0,"muEx5":0,"muAdd1":0,"muAdd2":0,"muAdd3":0,"faction":0,"zone":0},{"_id":196,"traitName":"Paranoid","traitDesc":"Constantly on edge, all Morale gains are reduced by 50%","characterEffectId":241,"traitScore":-1,"actionType":61,"resultType":0,"traitGroupId":13,"traitGroupId2":0,"muEvent1":0,"muEvent2":0,"muEx1":0,"muEx2":0,"muEx3":0,"muEx4":0,"muEx5":0,"muAdd1":0,"muAdd2":0,"muAdd3":0,"faction":0,"zone":0},{"_id":197,"traitName":"Dread Legacy","traitDesc":"Bearing a charter stained in the blood of xeno, gains extra Rep bonus with all factions in a quadrant for destroying a Xeno ship and a personal XP bonus","characterEffectId":0,"traitScore":3,"actionType":0,"resultType":0,"traitGroupId":22,"traitGroupId2":0,"muEvent1":0,"muEvent2":0,"muEx1":0,"muEx2":0,"muEx3":0,"muEx4":0,"muEx5":0,"muAdd1":0,"muAdd2":0,"muAdd3":0,"faction":0,"zone":0},{"_id":198,"traitName":"Inner Flame","traitDesc":"Resolute and unwavering in the hunt, +2 Resilience, +1 Fortitude, +2 Initiative, +15% Armor and Morale will never drop below 50","characterEffectId":1132,"traitScore":3,"actionType":61,"resultType":0,"traitGroupId":22,"traitGroupId2":0,"muEvent1":0,"muEvent2":0,"muEx1":0,"muEx2":0,"muEx3":0,"muEx4":0,"muEx5":0,"muAdd1":0,"muAdd2":0,"muAdd3":0,"faction":0,"zone":0},{"_id":199,"traitName":"Scrupulous","traitDesc":"A thorough and focused approach helps bring missions in successfully, gains +5% on all Mission payments (3 max)","characterEffectId":0,"traitScore":2,"actionType":11,"resultType":0,"traitGroupId":5,"traitGroupId2":0,"muEvent1":0,"muEvent2":0,"muEx1":0,"muEx2":0,"muEx3":0,"muEx4":0,"muEx5":0,"muAdd1":0,"muAdd2":0,"muAdd3":0,"faction":0,"zone":0},{"_id":200,"traitName":"Surehand","traitDesc":"20% chance to gain permanent +1 Gunnery Skill Bonus when leveling (max 12)","characterEffectId":0,"traitScore":2,"actionType":115,"resultType":0,"traitGroupId":5,"traitGroupId2":0,"muEvent1":0,"muEvent2":0,"muEx1":0,"muEx2":0,"muEx3":0,"muEx4":0,"muEx5":0,"muAdd1":0,"muAdd2":0,"muAdd3":0,"faction":0,"zone":0},{"_id":201,"traitName":"Bad Eyes","traitDesc":"","characterEffectId":242,"traitScore":-1,"actionType":0,"resultType":0,"traitGroupId":5,"traitGroupId2":0,"muEvent1":0,"muEvent2":0,"muEx1":0,"muEx2":0,"muEx3":0,"muEx4":0,"muEx5":0,"muAdd1":0,"muAdd2":0,"muAdd3":0,"faction":0,"zone":0},{"_id":202,"traitName":"Maimed","traitDesc":"","characterEffectId":243,"traitScore":-2,"actionType":0,"resultType":0,"traitGroupId":5,"traitGroupId2":0,"muEvent1":0,"muEvent2":0,"muEx1":0,"muEx2":0,"muEx3":0,"muEx4":0,"muEx5":0,"muAdd1":0,"muAdd2":0,"muAdd3":0,"faction":0,"zone":0},{"_id":203,"traitName":"Well-Rounded","traitDesc":"","characterEffectId":244,"traitScore":2,"actionType":0,"resultType":0,"traitGroupId":5,"traitGroupId2":0,"muEvent1":0,"muEvent2":0,"muEx1":0,"muEx2":0,"muEx3":0,"muEx4":0,"muEx5":0,"muAdd1":0,"muAdd2":0,"muAdd3":0,"faction":0,"zone":0},{"_id":204,"traitName":"Diggermind","traitDesc":"A natural knack for digging, gain +10% on Raw resource, Rare and Artifact rewards whenever Exploring (max 30%)","characterEffectId":245,"traitScore":1,"actionType":52,"resultType":0,"traitGroupId":5,"traitGroupId2":0,"muEvent1":0,"muEvent2":0,"muEx1":0,"muEx2":0,"muEx3":0,"muEx4":0,"muEx5":0,"muAdd1":0,"muAdd2":0,"muAdd3":0,"faction":0,"zone":0},{"_id":205,"traitName":"Wayfarer","traitDesc":"A wanderer and a seeker, may abandon the ship due to low Morale even when promoted to Officer","characterEffectId":246,"traitScore":-1,"actionType":0,"resultType":0,"traitGroupId":5,"traitGroupId2":0,"muEvent1":0,"muEvent2":0,"muEx1":0,"muEx2":0,"muEx3":0,"muEx4":0,"muEx5":0,"muAdd1":0,"muAdd2":0,"muAdd3":0,"faction":0,"zone":0},{"_id":206,"traitName":"Fast Talker","traitDesc":"Quick with words","characterEffectId":247,"traitScore":1,"actionType":0,"resultType":0,"traitGroupId":5,"traitGroupId2":0,"muEvent1":0,"muEvent2":0,"muEx1":0,"muEx2":0,"muEx3":0,"muEx4":0,"muEx5":0,"muAdd1":0,"muAdd2":0,"muAdd3":0,"faction":0,"zone":0},{"_id":207,"traitName":"Bulky","traitDesc":"","characterEffectId":248,"traitScore":1,"actionType":0,"resultType":0,"traitGroupId":5,"traitGroupId2":0,"muEvent1":0,"muEvent2":0,"muEx1":0,"muEx2":0,"muEx3":0,"muEx4":0,"muEx5":0,"muAdd1":0,"muAdd2":0,"muAdd3":0,"faction":0,"zone":0},{"_id":208,"traitName":"Self-Taught","traitDesc":"Independent thinker, +10% chance of gaining double XP","characterEffectId":249,"traitScore":2,"actionType":62,"resultType":0,"traitGroupId":5,"traitGroupId2":0,"muEvent1":0,"muEvent2":0,"muEx1":0,"muEx2":0,"muEx3":0,"muEx4":0,"muEx5":0,"muAdd1":0,"muAdd2":0,"muAdd3":0,"faction":0,"zone":0},{"_id":209,"traitName":"Flexible","traitDesc":"Pliable in thought and movement","characterEffectId":250,"traitScore":1,"actionType":0,"resultType":0,"traitGroupId":5,"traitGroupId2":0,"muEvent1":0,"muEvent2":0,"muEx1":0,"muEx2":0,"muEx3":0,"muEx4":0,"muEx5":0,"muAdd1":0,"muAdd2":0,"muAdd3":0,"faction":0,"zone":0},{"_id":210,"traitName":"Bloodstained","traitDesc":"","characterEffectId":251,"traitScore":0,"actionType":0,"resultType":0,"traitGroupId":5,"traitGroupId2":0,"muEvent1":0,"muEvent2":0,"muEx1":0,"muEx2":0,"muEx3":0,"muEx4":0,"muEx5":0,"muAdd1":0,"muAdd2":0,"muAdd3":0,"faction":0,"zone":0},{"_id":211,"traitName":"Ace Pilot","traitDesc":"Gain 5-10 Morale when launching a craft flight plan","characterEffectId":252,"traitScore":2,"actionType":107,"resultType":0,"traitGroupId":5,"traitGroupId2":0,"muEvent1":0,"muEvent2":0,"muEx1":0,"muEx2":0,"muEx3":0,"muEx4":0,"muEx5":0,"muAdd1":0,"muAdd2":0,"muAdd3":0,"faction":0,"zone":0},{"_id":212,"traitName":"Daredevil","traitDesc":"Gain 5-10 Morale when launching a craft flight plan","characterEffectId":253,"traitScore":1,"actionType":107,"resultType":0,"traitGroupId":5,"traitGroupId2":0,"muEvent1":0,"muEvent2":0,"muEx1":0,"muEx2":0,"muEx3":0,"muEx4":0,"muEx5":0,"muAdd1":0,"muAdd2":0,"muAdd3":0,"faction":0,"zone":0},{"_id":213,"traitName":"Lonehawk","traitDesc":"","characterEffectId":254,"traitScore":2,"actionType":0,"resultType":0,"traitGroupId":5,"traitGroupId2":0,"muEvent1":0,"muEvent2":0,"muEx1":0,"muEx2":0,"muEx3":0,"muEx4":0,"muEx5":0,"muAdd1":0,"muAdd2":0,"muAdd3":0,"faction":0,"zone":0},{"_id":214,"traitName":"Jyeeta Hide","traitDesc":"","characterEffectId":255,"traitScore":2,"actionType":0,"resultType":0,"traitGroupId":5,"traitGroupId2":0,"muEvent1":0,"muEvent2":0,"muEx1":0,"muEx2":0,"muEx3":0,"muEx4":0,"muEx5":0,"muAdd1":0,"muAdd2":0,"muAdd3":0,"faction":0,"zone":0},{"_id":215,"traitName":"Theoretician","traitDesc":"Acute observer and quick study, +2 Wisdom, +2 Resilience and gains +15% profit when selling Scientific Intel","characterEffectId":256,"traitScore":3,"actionType":0,"resultType":0,"traitGroupId":22,"traitGroupId2":0,"muEvent1":0,"muEvent2":0,"muEx1":0,"muEx2":0,"muEx3":0,"muEx4":0,"muEx5":0,"muAdd1":0,"muAdd2":0,"muAdd3":0,"faction":0,"zone":0},{"_id":216,"traitName":"Cerebral Seeker","traitDesc":"Thorough and exhaustive in the search for new knowledge, double the chance of drawing Scientific Intel while Exploring or during Orbital Salvage","characterEffectId":0,"traitScore":3,"actionType":0,"resultType":0,"traitGroupId":22,"traitGroupId2":0,"muEvent1":0,"muEvent2":0,"muEx1":0,"muEx2":0,"muEx3":0,"muEx4":0,"muEx5":0,"muAdd1":0,"muAdd2":0,"muAdd3":0,"faction":0,"zone":0},{"_id":217,"traitName":"Zendu Lineage","traitDesc":"Genetically encoded memories of a thousand years of Zendu ancestory","characterEffectId":1233,"traitScore":3,"actionType":0,"resultType":0,"traitGroupId":21,"traitGroupId2":0,"muEvent1":0,"muEvent2":0,"muEx1":0,"muEx2":0,"muEx3":0,"muEx4":0,"muEx5":0,"muAdd1":0,"muAdd2":0,"muAdd3":0,"faction":0,"zone":0},{"_id":218,"traitName":"Battle Proven","traitDesc":"Often set to a single, resolute purpose, +2 Fortitude, +2 Resilience, +2 Initiative, +20% Debuff Resist, Morale never breaks in Crew Combat ","characterEffectId":1257,"traitScore":3,"actionType":0,"resultType":0,"traitGroupId":22,"traitGroupId2":0,"muEvent1":0,"muEvent2":0,"muEx1":0,"muEx2":0,"muEx3":0,"muEx4":0,"muEx5":0,"muAdd1":0,"muAdd2":0,"muAdd3":0,"faction":0,"zone":0},{"_id":219,"traitName":"Undisputed Boarder","traitDesc":"Charging to battle even from the bridge of their ship, gains +20 Boarding, +1 Initiative and +5 Range Change in Ship Combat","characterEffectId":-232,"traitScore":3,"actionType":0,"resultType":0,"traitGroupId":22,"traitGroupId2":0,"muEvent1":0,"muEvent2":0,"muEx1":0,"muEx2":0,"muEx3":0,"muEx4":0,"muEx5":0,"muAdd1":0,"muAdd2":0,"muAdd3":0,"faction":0,"zone":0}]